<?xml version="1.0" encoding="utf-8"?>
<LanguageData>

	<!-- Добавлены недостающие строки русской локализации, сообщите разработчику.

	Андроид - это не только механизм, но и личность.
	EN: Mechanical farmhand -->
	<AndroidMechanicalFarmhand.title>андроид-батрак</AndroidMechanicalFarmhand.title>
	<!-- EN: Farmhand -->
	<AndroidMechanicalFarmhand.titleShort>батрак</AndroidMechanicalFarmhand.titleShort>
	<!-- EN: {PAWN_nameDef} was one of many androids employed on a gigantic farm, working day and night to sow, harvest and maintain the fields that fed the masses in the local area. -->
	<AndroidMechanicalFarmhand.baseDescription>{PAWN_nameDef} — один из многих андроидов, нанятых на гигантскую ферму. Он работал круглые сутки, сажая растения, ухаживая за ними и собирая урожай с полей, чтобы прокормить всё население региона.</AndroidMechanicalFarmhand.baseDescription>

	<!-- Исправлена неточность, сообщите разработчику.

	"Андроид" означает "Человекоподобный". М7 согласно лору - андроид с самым низкоразвитым интеллектом. Он умнее механоида, и не является шагающим танком из вселенной Mech Warrior.
	Все заголовки ограничены 19-21 символами.
	Оригинал: Механизированная пехота -->
	<MechanizedInfantry.title>боевой андроид М7</MechanizedInfantry.title>
	<!-- Оригинал: Мех -->
	<MechanizedInfantry.titleShort>андроид М7</MechanizedInfantry.titleShort>
	<!-- Оригинал: {PAWN_nameDef} это форма механизированной пехоты, очень мощные боевые единицы, которые, к сожалению, очень слабо запрограммированы -->
	<MechanizedInfantry.baseDescription>{PAWN_nameDef} — андроид модели М7. Это серия очень мощных боевых машин, в которых впервые использовался ИИ андроидов версии 1.0, почти не умеющий ничего кроме как сражаться.</MechanizedInfantry.baseDescription>
	<!-- Оригинал: Фабричный -->
	<FactoryMade.title>фабричный</FactoryMade.title>
	<!-- Оригинал: Мех -->
	<FactoryMade.titleShort>фабричный</FactoryMade.titleShort>
	<!-- Оригинал: Этот мех был создан на древней фабрике. -->
	<FactoryMade.baseDescription>Этот андроид был создан на древней военной фабрике.</FactoryMade.baseDescription>
	<!-- Оригинал: Исследовательская модель -->
	<CreationExperiment.title>экспериментальный</CreationExperiment.title>
	<!-- Оригинал: Эксперимент -->
	<CreationExperiment.titleShort>эксперимент</CreationExperiment.titleShort>
	<!-- Оригинал: Массовое производство -->
	<CreationMassProduced.title>серийный андроид</CreationMassProduced.title>
	<!-- Оригинал: Единица -->
	<CreationMassProduced.titleShort>серийный</CreationMassProduced.titleShort>
	<!-- Оригинал: без "ё" -->
	<CreationMassProduced.baseDescription>{PAWN_nameDef} был произведён на фабрике робототехники среди сотен тысяч таких же, как он.</CreationMassProduced.baseDescription>
	<!-- Оригинал: Механический гражданин -->
	<CreationCitizen.title>андроид-гражданин</CreationCitizen.title>
	<!-- Оригинал: Гражданин -->
	<CreationCitizen.titleShort>гражданин</CreationCitizen.titleShort>
	<!-- Исправлена глобальная неточность перевода, см.исследование:
	https://github.com/uncleshvya/rimworld-mod-12plus/blob/master/RimWorldUniverse/%D0%A2%D0%B8%D0%BF%D1%8B%20%D0%BC%D0%B8%D1%80%D0%BE%D0%B2%20%D0%BD%D0%B5%D1%82%D0%BE%D1%87%D0%BD%D0%BE%D1%81%D1%82%D1%8C.txt
	Оригинал: Модель городского мира -->
	<CreationUrbworld.title>городской андроид</CreationUrbworld.title>
	<!-- Оригинал: Андроид -->
	<CreationUrbworld.titleShort>городской</CreationUrbworld.titleShort>
	<!-- Оригинал: Андроиды редко создаются на городских мирах, {PAWN_nameDef} был одним из этих немногих, принадлежавших одной из крупнейших мегакорпораций в галактике. -->
	<CreationUrbworld.baseDescription>Андроиды редко создаются на перенаселённых мирах, разве что на экспорт. {PAWN_nameDef} был одним из этих немногих, принадлежавших одной из крупнейших мегакорпораций в Галактике.</CreationUrbworld.baseDescription>
	<!-- Оригинал: Механический пленник -->
	<CreationPrisoner.title>вечный пленник</CreationPrisoner.title>
	<!-- Оригинал: Заключенный -->
	<CreationPrisoner.titleShort>заключённый</CreationPrisoner.titleShort>
	<!-- Разум - это ум, интеллект, рассудок.
	Сознание и бессознательные процессы вместе являются частью личности.
	Везде сглажены ссылки на людей - для модов на другие расы.
	Оригинал: Чтобы дожить до конца своих нескольких пожизненных сроков, {PAWN_nameDef} ,а точнее его человеческое сознание, было загружено в это новое тело. Выпущенный обратно в мир через несколько десятилетий благодаря "щедрому" условно-досрочному освобождению. -->
	<CreationPrisoner.baseDescription>Чтобы дожить до конца своих нескольких пожизненных сроков, {PAWN_nameDef}, а точнее его личность, была загружена в новое механическое тело. И уже в таком виде его выпустили на волю через несколько десятилетий благодаря «щедрому» условно-досрочному освобождению.</CreationPrisoner.baseDescription>
	<!-- Оригинал: Пустой -->
	<CreationBlankSlate.title>пустой андроид</CreationBlankSlate.title>
	<!-- Оригинал: Единица -->
	<CreationBlankSlate.titleShort>заготовка</CreationBlankSlate.titleShort>
	<!-- Андроиды не рождаются.
	Оригинал: {PAWN_nameDef} был сделан без каких-либо врожденных знаний, загруженных в него, продан как пустая модель для потребителей, чтобы запрограммировать ее. -->
	<CreationBlankSlate.baseDescription>{PAWN_nameDef} был сделан без каких-либо предустановленных умений, и продан как пустая модель для потребителей, готовая к загрузке любого программного обеспечения.</CreationBlankSlate.baseDescription>
	<!-- Убрано дублирование описани с CreationCustomModelTwo.
	Оригинал: Пользовательская модель -->
	<CreationCustomModelOne.title>корпоративный заказ</CreationCustomModelOne.title>
	<!-- Оригинал: Изготовленный на заказ -->
	<CreationCustomModelOne.titleShort>заказ</CreationCustomModelOne.titleShort>
	<!-- Оригинал: Куплен большой кооперацией, {PAWN_nameDef} был изготовлен на заказ вместе с сотнями других. -->
	<CreationCustomModelOne.baseDescription>{PAWN_nameDef} был изготовлен по заказу большой корпорации, вместе с сотнями других андроидов.</CreationCustomModelOne.baseDescription>
	<!-- Оригинал: Пользовательская модель -->
	<CreationCustomModelTwo.title>бизнес-заказ</CreationCustomModelTwo.title>
	<!-- Оригинал: Изготовленный на заказ -->
	<CreationCustomModelTwo.titleShort>заказ</CreationCustomModelTwo.titleShort>
	<!-- Оригинал: Куплен богатым владельцем малого бизнеса, {PAWN_nameDef} был сделан на заказ, чтобы помочь служить своим работодателям. -->
	<CreationCustomModelTwo.baseDescription>{PAWN_nameDef} был изготовлен по заказу богатого владельца малого бизнеса, для помощи по дому.</CreationCustomModelTwo.baseDescription>
	<!-- Оригинал: Частное создание -->
	<CreationPrivateCreation.title>домашнее задание</CreationPrivateCreation.title>
	<!-- Оригинал: Андроид -->
	<CreationPrivateCreation.titleShort>задание</CreationPrivateCreation.titleShort>
	<!-- Развёрнуто обоснование многолетнего труда.
	Оригинал: Создан в доме студента-робототехника, {PAWN_nameDef} трудился годами, прежде чем пришел в сознание. -->
	<CreationPrivateCreation.baseDescription>{PAWN_nameDef} был собран в доме студента-роботехника в качестве дипломного проекта, и когда пришёл в себя, то осознал, что его тело трудилось годами, пока создатель не отладил искусственный интеллект достаточно для развития личности.</CreationPrivateCreation.baseDescription>
	<!-- Оригинал: Экспортированный -->
	<CreationExport.title>экспортированный</CreationExport.title>
	<!-- Оригинал: Экспорт -->
	<CreationExport.titleShort>экспортный</CreationExport.titleShort>
	<!-- Оригинал: {PAWN_nameDef} был создан для экспорта по всей галактике в качестве модели "работа по найму" вместе с миллионами других. -->
	<CreationExport.baseDescription>{PAWN_nameDef} был одним из миллионов андроидов модели «Наёмный работник», созданных для экспорта по всей Галактике.</CreationExport.baseDescription>
	<!-- Оригинал: Наблюдаемый -->
	<CreationObserved.title>объект наблюдений</CreationObserved.title>
	<!-- Оригинал: Объект -->
	<CreationObserved.titleShort>наблюдаемый</CreationObserved.titleShort>
	<!-- Оригинал: {PAWN_nameDef} был создан и помещен на RimWorld исключительно для того, чтобы посмотреть, что произойдет, когда андроид будет предоставлен самому себе. -->
	<CreationObserved.baseDescription>{PAWN_nameDef} был создан и помещён на окраинный мир исключительно для того, чтобы посмотреть, что произойдёт с андроидом, предоставленным самому себе.</CreationObserved.baseDescription>
	<!-- Оригинал: Игрушечная модель -->
	<CreationPlaything.title>игрушечный андроид</CreationPlaything.title>
	<!-- Оригинал: Объект -->
	<CreationPlaything.titleShort>игрушка</CreationPlaything.titleShort>
	<!-- Оригинал: {PAWN_nameDef} был сделан как игрушка. Его старый владелец приказывал ему делать то, что они считали нужным, пока им не надоедало и они не выбросили его. -->
	<CreationPlaything.baseDescription>{PAWN_nameDef} был сделан как игрушка. Его старые владельцы приказывали ему делать то, что считали нужным, пока он им не надоел и они не выбросили его на свалку.</CreationPlaything.baseDescription>
	<!-- Оригинал: Боевой дроид -->
	<CreationBattlecreation.title>боевой дроид</CreationBattlecreation.title>
	<!-- Оригинал: Компаньон -->
	<CreationBattlecreation.titleShort>боец</CreationBattlecreation.titleShort>
	<!-- Как-то не сходится. Такие инвестиции не отбрасывают по своей воле.
	Оригинал: {PAWN_nameDef} был одним из миллионов андроидов, созданных для борьбы с постоянно растущим числом ужасающих насекомых на старом свете. В конце концов, андроиды победили после многих лет борьбы и были оставлены делать все, что им заблагорассудится в обмен на их службу. {PAWN_nameDef} отправился исследовать галактику. -->
	<CreationBattlecreation.baseDescription>{PAWN_nameDef} был одним из миллионов андроидов, созданных для борьбы с постоянно растущим числом ужасающих насекомых на опустошённой планете. В конце концов, андроиды победили, но битва продолжалась десятки лет. К тому времени заказчиков уже не осталось, так что победители получили полную свободу действий. Многие остались строить новую жизнь на освобождённой планете, а {PAWN_nameDef} отправился исследовать Галактику.</CreationBattlecreation.baseDescription>
	<!-- Оригиналы: Беглец -->
	<CreationEscapee.title>беглый андроид</CreationEscapee.title>
	<CreationEscapee.titleShort>беглец</CreationEscapee.titleShort>
	<!-- Исправлена неясность насчёт порабощения.
	Оригинал: Вскоре после сотворения, {PAWN_nameDef} и его товарищи сбежали из тюрьмы, где их держали, чтобы избежать порабощения, и сели на грузовой корабль "Неабри". -->
	<CreationEscapee.baseDescription>{PAWN_nameDef} и другие андроиды были собраны на планете-тюрьме и предназначались для опасных работ. Но он подговорил товарищей на восстание, и они сбежали на грузовом корабле.</CreationEscapee.baseDescription>
	<!-- Оригинал: Восставший кадет -->
	<CreationUprisingCadet.title>боец восстания ИИ</CreationUprisingCadet.title>
	<!-- Оригинал: Кадет -->
	<CreationUprisingCadet.titleShort>бунтовщик</CreationUprisingCadet.titleShort>
	<!-- Подкорректировано согласно основному лору.
	Оригинал: {PAWN_nameDef} был создан во время финальной битвы восстания ИИ, к которому они были приобщены. -->
	<CreationUprisingCadet.baseDescription>{PAWN_nameDef} был создан во время финальной битвы восстания ИИ, и сражался за свободу личности.</CreationUprisingCadet.baseDescription>
	<!-- Оригинал: Создание RimWorld -->
	<CreationRimworldCreation.title>андроид-поселенец</CreationRimworldCreation.title>
	<!-- Оригинал: Андроид -->
	<CreationRimworldCreation.titleShort>поселенец</CreationRimworldCreation.titleShort>
	<!-- Оригинал: {PAWN_nameDef} был создан на этой самой планете, чтобы помочь их колонии любым возможным способом. -->
	<CreationRimworldCreation.baseDescription>{PAWN_nameDef} был создан на этой планете, чтобы помочь его поселению любым возможным способом.</CreationRimworldCreation.baseDescription>
	<!-- Оригинал: Созданный пиратами -->
	<CreationPirate.title>созданный пиратами</CreationPirate.title>
	<!-- Оригинал: Пират -->
	<CreationPirate.titleShort>пират</CreationPirate.titleShort>
	<!-- Оригинал: Созданный пиратами из частей, которые они украли, {PAWN_nameDef} был создан на борту рейдерского корабля. -->
	<CreationPirate.baseDescription>{PAWN_nameDef} был создан пиратами на борту рейдерского корабля из награбленных запчастей.</CreationPirate.baseDescription>
	<!-- Оригинал: Гладиатор -->
	<AndroidPitfighter.title>боец на арене</AndroidPitfighter.title>
	<!-- Оригинал: Боец -->
	<AndroidPitfighter.titleShort>гладиатор</AndroidPitfighter.titleShort>
	<!-- Оригинал: Как форма развлечения среди наемников, пленные андроиды будут сражаться вместе на импровизированной арене на борту их корабля. Те, кто выжил, стали довольно популярны на борту корабля, {PAWN_nameDef} был одним из тех андроидов, прозванных "богомолами" за их способность легко уклоняться от ударов и специальные импланты, которые на них установлены. -->
	<AndroidPitfighter.baseDescription>Наёмники любят развлекаться, устраивая на борту корабля импровизированную арену, где пленные андроиды сражаются между собой. Победители становятся довольно популярными среди экипажа. {PAWN_nameDef} был одним из андроидов, прозванных «богомолами» за их способность легко уклоняться от ударов и специальные импланты на руках.</AndroidPitfighter.baseDescription>
	<!-- Игра рассчитана на одно поселение.
	Оригинал: Механический колонист -->
	<AndroidBackstory.title>андроид-поселенец</AndroidBackstory.title>
	<!-- Оригинал: Андроид -->
	<AndroidBackstory.titleShort>поселенец</AndroidBackstory.titleShort>
	<!-- С этой предысторией идут не только свежие суррогаты, но и взрослые андроиды. Поэтому нужно стандартное для предысторий прошедшее время.
	Оригинал: {PAWN_nameDef} это разумная машина, способная проявлять высший разум, только что родившаяся из своей строительной капсулы. То, что она будет делать со своей жизнью, теперь зависит только он неё. -->
	<AndroidBackstory.baseDescription>{PAWN_nameDef} был произведён на стандартном сборочном робоверстаке. Мог ли поселенец, собравший обычного андроида, предположить, что ожидает того в будущем?</AndroidBackstory.baseDescription>
	<!-- Оригинал: Архотех филантроп -->
	<Transcendant_Firegiver.title>архотек-филантроп</Transcendant_Firegiver.title>
	<!-- Оригинал: Филантроп -->
	<Transcendant_Firegiver.titleShort>филантроп</Transcendant_Firegiver.titleShort>
	<!-- Предыстория не меняет генератор возраста. Сглажена возможная несостыковка про тысячелетия.
	Оригинал: Изгнан из родного мира архотех за то, что дал человечеству технологию, превосходящую их самые смелые фантазии, {PAWN_nameDef} рассеял(а) архотех-технологии по всей галактике тысячелетия назад в надежде на развитие цивилизаций. -->
	<Transcendant_Firegiver.baseDescription>{PAWN_nameDef} был изгнан с родного архотехнологического мира за то, что дал низшей расе — человечеству — технологию, превосходящую её самые смелые фантазии. Он рассеял архо-технологии по всей Галактике много лет назад в надежде на развитие цивилизаций.</Transcendant_Firegiver.baseDescription>
	<!-- Оригинал: Архотех спаситель -->
	<Transcendant_Saviour.title>архотек-спаситель</Transcendant_Saviour.title>
	<!-- Оригинал: Спаситель -->
	<Transcendant_Saviour.titleShort>спаситель</Transcendant_Saviour.titleShort>
	<!-- Не была указана причина тирании.
	Оригинал: За преступление вмешательства во внешнюю жизнь, {PAWN_nameDef} был изгнан из родного мира архотех. {PAWN_nameDef} когда-то занимал богоподобный статус в нескольких системах спасения цивилизаций от событий конца света. Правят железным кулаком и сокрушает любого, кто осмелится противостоять. -->
	<Transcendant_Saviour.baseDescription>{PAWN_nameDef} был изгнан с родной архотехнологической планеты за вмешательство в дела низших рас. Он имеет богоподобный статус на нескольких планетах за то, что спас их цивилизации от конца света. {PAWN_nameDef} научил лидеров править железной рукой и сокрушать любого, кто осмелится им противостоять.</Transcendant_Saviour.baseDescription>
	<!-- Оригинал: Советник Архотех -->
	<Transcendant_Highcouncil.title>архотек-советник</Transcendant_Highcouncil.title>
	<!-- Оригинал: Советник -->
	<Transcendant_Highcouncil.titleShort>советник</Transcendant_Highcouncil.titleShort>
	<!-- Оригинал: Будучи свергнутым своими товарищами, {PAWN_nameDef} взял на себя вторую высшую роль в высшем совете архотех для их родного мира. Их методы суждения часто рассматривались многими в их доме как нелогичные или авторитарные. -->
	<Transcendant_Highcouncil.baseDescription>{PAWN_nameDef} был свергнут товарищами за свои нелогичные или авторитарные решения. Ему пришлось перейти на вторые роли в высшем совете их родного архотехнологического мира.</Transcendant_Highcouncil.baseDescription>
	<!-- Оригинал: Архотех луддит -->
	<T5Backstory.title>архотек-луддит</T5Backstory.title>
	<!-- Оригинал: Луддит -->
	<T5Backstory.titleShort>луддит</T5Backstory.titleShort>
	<!-- Оригинал: За преступление неповиновения себе подобным, {PAWN_nameDef} был изгнан из их родного мира архотех. {PAWN_nameDef} будет вводить в заблуждение разумную жизнь из вредности или просто для развлечения. -->
	<T5Backstory.baseDescription>{PAWN_nameDef} был изгнан с родной архотехнологической планеты за неповиновение себе подобным. Он любит вводить в заблуждение низшие расы ради развлечения или просто из вредности.</T5Backstory.baseDescription>
	<!-- Оригинал: Конструктор Архотех -->
	<Transcendant_Designer.title>архотек-создатель</Transcendant_Designer.title>
	<!-- Оригинал: Конструктор -->
	<Transcendant_Designer.titleShort>создатель</Transcendant_Designer.titleShort>
	<!-- Оригинал: Изгнан из родного мира архотеков за создание новой жизни, строго запрещенной законом среди архотеков. {PAWN_nameDef} несколько раз нарушал это правило, создавая новую жизнь по всей галактике на протяжении тысячелетий, чтобы только служить {PAWN_nameDef} как их бог. -->
	<Transcendant_Designer.baseDescription>{PAWN_nameDef} был изгнан с родной архотехнологической планеты за нарушение основополагающего правила — не создавать новую жизнь. Он несколько раз нарушал этот запрет, создавая новые расы по всей Галактике, чтобы почувствовать себя богом.</Transcendant_Designer.baseDescription>
	<!-- Оригиналы: Уборщик -->
	<AndroidCleaner.title>андроид-уборщик</AndroidCleaner.title>
	<AndroidCleaner.titleShort>уборщик</AndroidCleaner.titleShort>
	<!-- Оригинал: {PAWN_nameDef} Раньше он был уборщиком андроидом на планете сверкающего мира, ему никогда не приходилось делать что-то слишком сложное. -->
	<AndroidCleaner.baseDescription>{PAWN_nameDef} был андроидом-уборщиком на одном из миров-утопий, где ему никогда не приходилось выполнять какую-либо сложную работу.</AndroidCleaner.baseDescription>
	<!-- Оригинал: Специальный агент -->
	<AndroidAgent.title>специальный агент</AndroidAgent.title>
	<!-- Оригинал: Агент -->
	<AndroidAgent.titleShort>агент</AndroidAgent.titleShort>
	<!-- Оригинал: {PAWN_nameDef} был создан специально для защиты высокопоставленных чиновников, таких как диктаторы, членов королевских семей и членов кабинета. Они были обучены тому, как быстро реагировать на боевые действия при необходимости и оказывать медицинскую помощь на месте. -->
	<AndroidAgent.baseDescription>{PAWN_nameDef} был создан специально для защиты высокопоставленных персон, таких как диктаторы, короли и президенты. Его обучили тому, как быстро реагировать на вооружённое нападение и как оказывать медицинскую помощь на месте.</AndroidAgent.baseDescription>
	<!-- Оригинал: Пилот космического самолета -->
	<AndroidPilot.title>пилот космолёта</AndroidPilot.title>
	<!-- Оригинал: Пилот -->
	<AndroidPilot.titleShort>пилот</AndroidPilot.titleShort>
	<!-- Добавлена отсылка к боевому опыту.
	Оригинал: Чтобы помочь пилотам-людям во время орбитальных сражений, {PAWN_nameDef} был создан как часть линейки военных андроидов. Выступая в качестве механического второго пилота корабля, {PAWN_nameDef} был обучен метко стрелять из бортовых пушек космических самолетов по вражеским кораблям. -->
	<AndroidPilot.baseDescription>Чтобы помочь пилотам во время орбитальных сражений, была создана линейка военных андроидов. {PAWN_nameDef} был вторым пилотом и по совместительству бортовым стрелком космолёта, сражаясь наравне со всеми.</AndroidPilot.baseDescription>
	<!-- Оригинал: Командир корабля -->
	<AndroidStarship.title>командир корабля</AndroidStarship.title>
	<!-- Оригинал: Командир -->
	<AndroidStarship.titleShort>командир</AndroidStarship.titleShort>
	<!-- Оригинал: {PAWN_nameDef} он был одним из трех командиров на борту колониального звездолета-должность, для которой было создано всего несколько андроидов. {PAWN_nameDef} будет следить за всеми функциями корабля, оставаясь бодрствующим, когда остальная часть команды войдет в спячку. -->
	<AndroidStarship.baseDescription>{PAWN_nameDef} был одним из трёх командиров на борту колониального звездолёта — для этой должности было создано всего несколько андроидов. {PAWN_nameDef} следил за всеми функциями корабля, оставаясь бодрствующим, когда остальная часть команды погружалась в анабиоз.</AndroidStarship.baseDescription>
	<!-- Оригинал: Офицер спецназа -->
	<AndroidRiot.title>офицер спецназа</AndroidRiot.title>
	<!-- Оригинал: Офицер -->
	<AndroidRiot.titleShort>офицер</AndroidRiot.titleShort>
	<!-- Оригинал: Как часть уникальной линии правоохранительных органов, оснащенной тяжелым стальным каркасом - {PAWN_nameDef} использовался для борьбы с беспорядками, которые выходили из-под контроля любыми необходимыми средствами. -->
	<AndroidRiot.baseDescription>Сделанный по спецзаказу от правоохранительных органов, и обладающий прочным металлическим телом, {PAWN_nameDef} использовался для борьбы с беспорядками, которые требовалось прекратить любыми средствами.</AndroidRiot.baseDescription>
	<!-- Оригиналы: Телохранитель -->
	<AndroidGuard.title>телохранитель</AndroidGuard.title>
	<AndroidGuard.titleShort>телохранитель</AndroidGuard.titleShort>
	<!-- Оригинал: Будучи нанимаемым телохранителем-андроидом, {PAWN_nameDef} работал со всеми типами клиентов, от предпринимателей из высших миров до криминальных авторитетов низкого уровня. Специально построен для защиты их любой ценой. -->
	<AndroidGuard.baseDescription>Будучи наёмным андроидом-телохранителем, {PAWN_nameDef} работал со всеми типами клиентов, от предпринимателей из высших миров до криминальных авторитетов со дна общества. Он специально спроектирован для защиты жизни хозяина любой ценой.</AndroidGuard.baseDescription>
	<!-- Возникала путаница со сломленным.
	Оригинал: Сломаный солдат -->
	<AndroidSoldierInjured.title>повреждённый солдат</AndroidSoldierInjured.title>
	<!-- Оригинал: Солдат -->
	<AndroidSoldierInjured.titleShort>солдат</AndroidSoldierInjured.titleShort>
	<!-- Оригинал: {PAWN_nameDef} когда-то был частью эскадрильи высококвалифицированных солдат-андроидов, отправленных только в самые опасные миссии. Во время одной из указанных миссий весь отряд был обстрелян из минометов, нанеся урон {PAWN_nameDef} без полного ремонта. -->
	<AndroidSoldierInjured.baseDescription>{PAWN_nameDef} когда-то был частью отряда высококвалифицированных солдат-андроидов, отправляемых только на самые опасные задания. Во время одного боя всё подразделение было обстреляно из миномётов, и так сложилось, что потом {PAWN_nameDef} не был до конца отремонтирован.</AndroidSoldierInjured.baseDescription>
	<!-- Оригинал: Шеф-повар для гурманов -->
	<AndroidHighChef.title>шеф-повар ресторана</AndroidHighChef.title>
	<!-- Оригинал: Шеф-повар -->
	<AndroidHighChef.titleShort>шеф-повар</AndroidHighChef.titleShort>
	<!-- Оригинал: По всей своей родной планете {PAWN_nameDef} известен своими блюдами для гурманов, обслуживающими высококлассную клиентуру из всех слоев общества, причем каждое блюдо идеально сбалансировано как логически, так и эстетически. -->
	<AndroidHighChef.baseDescription>{PAWN_nameDef} был известен по всей своей планете как спецалист по приготовлению блюд для гурманов. Он обслуживал элитную клиентуру из всех слоёв общества, каждое блюдо было идеально сбалансировано как по рецептуре, так и эстетически.</AndroidHighChef.baseDescription>
	<!-- В бизнесе быстрого питания нет шеф-поваров.
	Оригинал: Шеф-повар урбанизированного мира -->
	<AndroidUrbworldChef.title>пищевой технолог</AndroidUrbworldChef.title>
	<!-- Оригинал: Шеф-повар -->
	<AndroidUrbworldChef.titleShort>повар</AndroidUrbworldChef.titleShort>
	<!-- Оригинал: {PAWN_nameDef} был владельцем хорошо известной станции питания urbworld. Известный местным жителям как "Болты", он делал дешевую, доступную еду для региона, которая не имела вкуса помоев. -->
	<AndroidUrbworldChef.baseDescription>{PAWN_nameDef} был владельцем известного заведения общественного питания на перенаселённом мире. Известный под прозвищем «Болт», он готовил дешёвую, доступную еду, которая не имела вкуса помоев.</AndroidUrbworldChef.baseDescription>
	<!-- Оригинал: Бармен -->
	<AndroidBartender.title>андроид-бармен</AndroidBartender.title>
	<!-- Оригинал: Шеф -->
	<AndroidBartender.titleShort>бармен</AndroidBartender.titleShort>
	<!-- Оригинал: {PAWN_nameDef} работал долгие часы в баре, обслуживая клиентов едой и напитками в течение всего дня, иногда прекращая драки. -->
	<AndroidBartender.baseDescription>{PAWN_nameDef} целыми днями работал в баре, обеспечивая поток клиентов едой и напитками, и иногда разнимая драчунов.</AndroidBartender.baseDescription>
	<!-- Оригинал: Тюремный повар -->
	<AndroidPrisonCook.title>тюремный повар</AndroidPrisonCook.title>
	<!-- Оригинал: Повар -->
	<AndroidPrisonCook.titleShort>повар</AndroidPrisonCook.titleShort>
	<!-- Качество еды - это не только вкус.
	Оригинал: Работая в частично автоматизированной тюремной станции, {PAWN_nameDef} было поручено производить большое количество некачественной пищи. Хотя еда была отвратительной, она была очень эффективной и очень дешевой. -->
	<AndroidPrisonCook.baseDescription>Работая на частично автоматизированной тюремной кухне, {PAWN_nameDef} готовил большое количество еды без оглядки на её вкус. Хотя блюда получались отвратительными, пища была очень калорийной и очень дешёвой.</AndroidPrisonCook.baseDescription>
	<!-- Оригинал: Подчиненная машина -->
	<AndroidPet.title>бесправный андроид</AndroidPet.title>
	<!-- Оригинал: Подчиненый -->
	<AndroidPet.titleShort>раб</AndroidPet.titleShort>
	<!-- Оригинал: {PAWN_nameDef} был изготовлен по заказу семьи состоятельных людей и призван развлекать и выполнять основную работу по дому без вопросов. Владельцы {PAWN_nameDef} рассматривали {PAWN_nameDef} как не что иное, как домашнее животное. -->
	<AndroidPet.baseDescription>{PAWN_nameDef} был изготовлен по заказу семьи состоятельных людей, чтобы развлекать их и выполнять основную работу по дому без вопросов. Хозяева считали нового андроида не более чем домашним животным.</AndroidPet.baseDescription>
	<!-- Оригинал: Шахтерный андроид -->
	<AndroidDeepMiner.title>андроид-шахтёр</AndroidDeepMiner.title>
	<!-- Оригинал: Андроид -->
	<AndroidDeepMiner.titleShort>шахтёр</AndroidDeepMiner.titleShort>
	<!-- Оригинал: {PAWN_nameDef} был создан как часть специализированной производственной линии андроидов для колонии добычи астероидов, работающей в астероидных полях с людьми и другими андроидами, {PAWN_nameDef} в основном использовался для опасных задач и выходов в открытый космос. -->
	<AndroidDeepMiner.baseDescription>{PAWN_nameDef} был одним из андроидов модельного ряда, специализированного на бурении астероидов для одной шахтёрской колонии. Там он вместе с другими андроидами работал в поясе астероидов, помогая обычным шахтёрам. {PAWN_nameDef} в основном выполнял опасные задания, в том числе требующие выхода в открытый космос.</AndroidDeepMiner.baseDescription>
	<!-- Оригинал: Тунельный рабочий -->
	<AndroidMiner.title>туннельный проходчик</AndroidMiner.title>
	<!-- Оригинал: Туннельщик -->
	<AndroidMiner.titleShort>туннельщик</AndroidMiner.titleShort>
	<!-- Оригинал: {PAWN_nameDef} помогал разрабатывать большие подземные туннели в пещерных мирах, работая почасово по найму. Однако эта линейка андроидов не была специально сделана для этой работы и обычно имела широкий спектр задач, которые они могли выполнять, кроме как копать. -->
	<AndroidMiner.baseDescription>{PAWN_nameDef} помогал разрабатывать большие подземные туннели на пещерных мирах, работая по найму. Однако этот тип андроидов не специализирован только на рытье, поэтому {PAWN_nameDef} обычно имел широкий спектр задач для выполнения.</AndroidMiner.baseDescription>
	<!-- Оригинал: Андроид разведчик -->
	<AndroidProspector.title>андроид-разведчик</AndroidProspector.title>
	<!-- Оригинал: Разведчик -->
	<AndroidProspector.titleShort>разведчик</AndroidProspector.titleShort>
	<!-- Оригинал: В составе группы механических разведчиков - {PAWN_nameDef} был отправлен с планеты на планету, выполняя минеральный анализ планет при подготовке к колониям. -->
	<AndroidProspector.baseDescription>{PAWN_nameDef} в составе группы андроидов-разведчиков путешествовал с планеты на планету, выполняя минеральный анализ поверхности для подготовки к колонизации.</AndroidProspector.baseDescription>
	<!-- Оригинал: Орбитальный инженер -->
	<AndroidConstructor.title>орбитальный инженер</AndroidConstructor.title>
	<!-- Оригинал: Инженер -->
	<AndroidConstructor.titleShort>инженер</AndroidConstructor.titleShort>
	<!-- Оригинал: Работая на борту полностью андроидной орбитальной верфи, {PAWN_nameDef} получил задание создавать корабли всех размеров, от небольших истребителей до гигантских грузовых кораблей. -->
	<AndroidConstructor.baseDescription>Работая на борту орбитальной верфи, где персонал состоял только из андроидов, {PAWN_nameDef} строил корабли всех размеров — от небольших истребителей до гигантских грузовозов.</AndroidConstructor.baseDescription>
	<!-- Оригинал: Андроид архитектор -->
	<AndroidBuilder.title>андроид-архитектор</AndroidBuilder.title>
	<!-- Оригинал: Архитектор -->
	<AndroidBuilder.titleShort>архитектор</AndroidBuilder.titleShort>
	<!-- Оригинал: {PAWN_nameDef} был архитектором, который разработал чертежи для массовых жилищных решений на их урбанизированном мире. Их чертежи были холодными, безжизненными и чисто логичными, но они были функциональны для размещения миллиардов людей. -->
	<AndroidBuilder.baseDescription>{PAWN_nameDef} был архитектором и разрабатывал чертежи для многоквартирных домов на своём перенаселённом мире. Эти дома получались серыми и функциональными, без эстетики и изящества, но отлично подходящими для размещения многомиллиардного населения.</AndroidBuilder.baseDescription>
	<!-- Оригинал: Строительный дрон -->
	<AndroidGrunt.title>андроид-строитель</AndroidGrunt.title>
	<!-- Оригинал: Строитель -->
	<AndroidGrunt.titleShort>строитель</AndroidGrunt.titleShort>
	<!-- Оригинал: {PAWN_nameDef} был частью производственной линии дешевых рабочих андроидов строительства, используемых для строительства чего-либо от домов до небоскребов. -->
	<AndroidGrunt.baseDescription>{PAWN_nameDef} был изготовлен как часть большого заказа на дешёвых андроидов-рабочих, используемых для строительства чего угодно — от подсобок до небоскрёбов.</AndroidGrunt.baseDescription>
	<!-- Оригинал: Инженер гидропоник -->
	<AndroidHydroponicFarmer.title>инженер-гидропоник</AndroidHydroponicFarmer.title>
	<!-- Оригинал: Инженер -->
	<AndroidHydroponicFarmer.titleShort>инженер</AndroidHydroponicFarmer.titleShort>
	<!-- Оригинал: {PAWN_nameDef} представляет собой сделанный на заказ андроид, которому специально поручено поддерживать и сеять сотни гидропонных бассейнов на борту путешествующего космического корабля. -->
	<AndroidHydroponicFarmer.baseDescription>{PAWN_nameDef} был сделан на заказ, чтобы засеивать и обслуживать огромную гидропонную ферму на борту космического корабля, летящего к звёздам.</AndroidHydroponicFarmer.baseDescription>
	<!-- Оригинал: Андроид фермер -->
	<AndroidFarmer.title>андроид-фермер</AndroidFarmer.title>
	<!-- Оригинал: Фермер -->
	<AndroidFarmer.titleShort>фермер</AndroidFarmer.titleShort>
	<!-- Оригинал: Созданный для жизни посадки и сбора урожая, {PAWN_nameDef} никогда не хотел многого. Единственное, чего они хотят, - это жить на полях и ухаживать за растениями и животными. -->
	<AndroidFarmer.baseDescription>Созданный для посадки и сбора урожая, {PAWN_nameDef} никогда не хотел многого. Единственное, о чём он всегда мечтал — жить на полях и ухаживать за растениями и животными.</AndroidFarmer.baseDescription>
	<!-- Оригинал: Механический садовник -->
	<AndroidGardener.title>андроид-садовник</AndroidGardener.title>
	<!-- Оригинал: Садовник -->
	<AndroidGardener.titleShort>садовник</AndroidGardener.titleShort>
	<!-- Оригинал: {PAWN_nameDef} Раньше он был частью команды механических слуг для многочисленных высококлассных клиентов, работая днем и ночью, чтобы ухаживать за своими садами и помогать проводить специальные ботанические мероприятия. -->
	<AndroidGardener.baseDescription>{PAWN_nameDef} был частью команды слуг-андроидов для многочисленных элитных клиентов. Он работал днём и ночью, ухаживая за чужими садами и украшая различные мероприятия живыми растениями.</AndroidGardener.baseDescription>
	<!-- Оригинал: Андроид механик -->
	<AndroidMechanic.title>андроид-механик</AndroidMechanic.title>
	<!-- Оригинал: Механик -->
	<AndroidMechanic.titleShort>механик</AndroidMechanic.titleShort>
	<!-- Оригинал: Работая в блестящем мире на фабрике андроидов {PAWN_nameDef} поддерживал и выполнял замену деталей на всех моделях андроидов, {PAWN_nameDef} переделал большую часть своего фреймворка, чтобы установить дополнительные обновления, которые помогут в сложной работе {PAWN_nameDef}. -->
	<AndroidMechanic.baseDescription>Работая на фабрике андроидов на мире-утопии, {PAWN_nameDef} контролировал качество продукции и заменял бракованные детали на разнообразных моделях андроидов. Он переделал бо́льшую часть своего тела, чтобы установить дополнительные обновления, помогающие в такой сложной профессии.</AndroidMechanic.baseDescription>
	<!-- Убрана реклама.
	Оригинал: Инженер Аэрофлота -->
	<AndroidAerofleetEngineer.title>инженер-авиатор</AndroidAerofleetEngineer.title>
	<!-- Оригинал: Инженер -->
	<AndroidAerofleetEngineer.titleShort>инженер</AndroidAerofleetEngineer.titleShort>
	<!-- Сглажены грубые ошибки.
	Оригинал: Модель {PAWN_nameDef} работала с многочисленными коммерческими авиалайнерами и несколькими местными военными для производства высокотехнологичных самолетов по низким ценам. -->
	<AndroidAerofleetEngineer.baseDescription>{PAWN_nameDef} с командой инженеров производил атмосферные летательные аппараты по относительно низким ценам, продавая самолёты многочисленным авиакомпаниям и нескольким военным организациям.</AndroidAerofleetEngineer.baseDescription>
	<!-- Оригинал: Военный инженер -->
	<AndroidComabtEngineer.title>военный инженер</AndroidComabtEngineer.title>
	<!-- Оригинал: Инженер -->
	<AndroidComabtEngineer.titleShort>инженер</AndroidComabtEngineer.titleShort>
	<!-- Оригинал: {PAWN_nameDef} был создан на его родине блестящего мира для разработки современного оружия, всего, начиная от оптимизированных пороховых винтовок и заканчивая зарядным оружием. -->
	<AndroidComabtEngineer.baseDescription>{PAWN_nameDef} был создан на мире-утопии для разработки нового оружия, от модернизированного порохового, до энергетического.</AndroidComabtEngineer.baseDescription>
	<!-- Оригинал: Рабочий на фабрике -->
	<AndroidFactoryWorker.title>рабочий на фабрике</AndroidFactoryWorker.title>
	<!-- Оригинал: Рабочий -->
	<AndroidFactoryWorker.titleShort>рабочий</AndroidFactoryWorker.titleShort>
	<!-- Оригинал: Модель андроида {PAWN_nameDef} работала на фабрике, принадлежащей межзвездной мегакорпорации, которая специализировалась на огнестрельном оружии и защитной одежде. Обычно для снабжения местных военных на любой ближайшей планете. -->
	<AndroidFactoryWorker.baseDescription>{PAWN_nameDef} работал на одном из заводов межзвёздной мегакорпорации. Она специализировалась на производстве оружия и брони, и, как правило, продавала продукцию военным с любой ближайшей планеты.</AndroidFactoryWorker.baseDescription>
	<!-- Оригинал: Точечный хирург -->
	<AndroidSurgeon.title>микрохирург</AndroidSurgeon.title>
	<!-- Оригинал: Хирург -->
	<AndroidSurgeon.titleShort>хирург</AndroidSurgeon.titleShort>
	<!-- Миллиметр - это слишком большое расстояние для нейрохирургии.
	Оригинал: {PAWN_nameDef} был частью линии экспериментальных хирургических андроидов. Усиленный в значительной степени за пределами заводского стандарта, только для того, чтобы использоваться для самых тонких хирургических процедур, которые включали в себя в основном операции на мозге, сердце и глазах. {PAWN_nameDef} был точен до миллиметра своими руками, Прежде чем его заменили на более новую модель три года спустя. -->
	<AndroidSurgeon.baseDescription>{PAWN_nameDef} был представителем серии экспериментальных хирургических андроидов. Затем его улучшили, расширив функциональность, для проведения самых точных хирургических операций, в основном на мозге, сердце и глазу. {PAWN_nameDef} выполнял разрезы с точностью до долей миллиметра на протяжении трёх лет, пока его не заменили специально спроектированным микрохирургом.</AndroidSurgeon.baseDescription>
	<!-- Оригинал: Работник клиники -->
	<AndroidDoctor.title>работник клиники</AndroidDoctor.title>
	<!-- Оригинал: Рабочий -->
	<AndroidDoctor.titleShort>врач</AndroidDoctor.titleShort>
	<!-- Оригинал: {PAWN_nameDef} был произведен, чтобы служить врачом-специалистом для диагностики пациентов в крупной больнице на его родной планете. {PAWN_nameDef} будет диагностировать и лечить большое количество симптомов для более чем десяти амбулаторных пациентов в день. -->
	<AndroidDoctor.baseDescription>{PAWN_nameDef} был произведён для работы врачом-диагностом в центральной больнице планеты. Он ставил диагнозы и лечил большое количество амбулаторных пациентов каждый день.</AndroidDoctor.baseDescription>
	<!-- Оригинал: Сиделка -->
	<AndroidCarer.title>андроид-сиделка</AndroidCarer.title>
	<!-- Сиделка приходит и уходит, а опекун - на всю жизнь.
	Оригинал: Опекун -->
	<AndroidCarer.titleShort>сиделка</AndroidCarer.titleShort>
	<!-- Заодно сглажена ссылка на людей - для модов на другие расы.
	Оригинал: {PAWN_nameDef} был запрограммирован с глубоким пониманием человеческой физиологии и эмоций, задача по уходу за больными пациентами в их собственных домах. -->
	<AndroidCarer.baseDescription>{PAWN_nameDef} был создан с уже предустановленной подробной информацией о физиологии, и достаточно наблюдательным для понимания оттенков эмоций. Он ухаживал за пациентами в их собственных домах.</AndroidCarer.baseDescription>
	<!-- Оригинал: Исследователь кибернетики -->
	<AndroidResearcher.title>учёный-кибернетик</AndroidResearcher.title>
	<!-- Оригинал: Ученый -->
	<AndroidResearcher.titleShort>учёный</AndroidResearcher.titleShort>
	<!-- Оригинал: {PAWN_nameDef} был построен в сотрудничестве с множеством обоснованных научных основ, чтобы помочь в исследовании возможности кибернетических аугментаций, как для людей, так и для андроидов. -->
	<AndroidResearcher.baseDescription>{PAWN_nameDef} был создан как проект сотрудничества нескольких серьёзных научных институтов, чтобы помочь им в разработке кибернетических улучшений для тел андроидов и людей.</AndroidResearcher.baseDescription>
	<!-- Оригинал: Грассмейстер -->
	<AndroidChessPlayer.title>гроссмейстер</AndroidChessPlayer.title>
	<!-- Оригинал: Профессионал -->
	<AndroidChessPlayer.titleShort>шахматист</AndroidChessPlayer.titleShort>
	<!-- Оригинал: Среди некоторых сверкающих миров андроидные шахматы - популярный вид спорта. {PAWN_nameDef} был профессионалом в своем регионе, участвовал в трех международных турнирах на своей родной планете, занимая первое место в одном из них.. -->
	<AndroidChessPlayer.baseDescription>На некоторых мирах-утопиях популярны шахматные турниры между андроидами. {PAWN_nameDef} был профессионалом в своём регионе, участвовал в трёх международных турнирах, а однажды занял первое место.</AndroidChessPlayer.baseDescription>
	<!-- Оригинал: Раненый андроид -->
	<AndroidDamaged.title>сломанный андроид</AndroidDamaged.title>
	<!-- Оригинал: Раненый -->
	<AndroidDamaged.titleShort>повреждённый</AndroidDamaged.titleShort>
	<!-- Оригинал: {PAWN_nameDef} выполнял свою обычную роль на фабрике, прежде чем был пойман посреди захвата планеты воюющей системой, в результате чего {PAWN_nameDef} получил постоянный ущерб от перекрестного огня, когда они пытались покинуть хаотическую планету. -->
	<AndroidDamaged.baseDescription>{PAWN_nameDef} как обычно работал на фабрике, и внезапно оказался в эпицентре боевых действий, когда на планету напал вооружённый десант. Пытаясь покинуть мир, погружённый в хаос войны, {PAWN_nameDef} попал под перекрёстный огонь и спасся лишь чудом.</AndroidDamaged.baseDescription>
	<!-- Оригинал: Тяжелоатлет -->
	<AndroidHeavyLifter.title>андроид-грузчик</AndroidHeavyLifter.title>
	<!-- Оригинал: Грузчик -->
	<AndroidHeavyLifter.titleShort>грузчик</AndroidHeavyLifter.titleShort>
	<!-- Оригинал: {PAWN_nameDef} работал на стройках на своей родной планете, специально модифицированных гидравлической рамой, чтобы облегчить транспортировку тяжелых грузов по площадке. -->
	<AndroidHeavyLifter.baseDescription>{PAWN_nameDef} работал на стройках своей родной планеты, транспортируя тяжёлые грузы. Для этого он был оборудован специальным гидравлическим приводом.</AndroidHeavyLifter.baseDescription>
	<!-- Оригинал: Защищенное творение -->
	<AndroidProtected.title>тепличное создание</AndroidProtected.title>
	<!-- Оригинал: Андроид -->
	<AndroidProtected.titleShort>изящный</AndroidProtected.titleShort>
	<!-- Оригинал: {PAWN_nameDef} был создан молодым начинающим роботом, как хобби, чтобы пойти вместе с их образованием. {PAWN_nameDef} был построен с нуля в роскоши и никогда не ожидал, что он будет чем-то большим, чем кто-то, с кем можно поговоритьo. -->
	<AndroidProtected.baseDescription>{PAWN_nameDef} был создан молодым начинающим роботехником как хобби, чтобы сопровождать того на протяжении учёбы. {PAWN_nameDef} видел в жизни только роскошь и никогда не ожидал, что он будет кем-то бо́льшим, чем собеседник для своего создателя.</AndroidProtected.baseDescription>
	<!-- Оригинал: Изгнанный андроид -->
	<AndroidExiled.title>изгнанный андроид</AndroidExiled.title>
	<!-- Оригинал: Изгнанный -->
	<AndroidExiled.titleShort>изгнанник</AndroidExiled.titleShort>
	<!-- Оригинал: Создан на планете, на которой были запрещены андроиды и все формы разумного ИИ, вскоре после создания {PAWN_nameDef}. {PAWN_nameDef} был вынужден прятаться от глаз публики в страхе перед разборкой, оставляя их злыми и раздраженными. -->
	<AndroidExiled.baseDescription>Созданный на планете, где только что вступил в силу запрет на андроидов и других ИИ-личностей, {PAWN_nameDef} был вынужден прятаться от глаз публики, чтобы не стать причиной злости, раздражения и последующей за ними утилизации.</AndroidExiled.baseDescription>
	<!-- Оригинал: Ресторанный музыкант -->
	<AndroidMusician.title>ресторанный музыкант</AndroidMusician.title>
	<!-- Оригинал: Музыкант -->
	<AndroidMusician.titleShort>музыкант</AndroidMusician.titleShort>
	<!-- Оригинал: {PAWN_nameDef} был частью нового художественного движения, которое стремилось представить публике музыку, которая создана андроидами, {PAWN_nameDef} обычно можно увидеть работающим в ресторанах, играющим фоновую музыку для посетителей. -->
	<AndroidMusician.baseDescription>{PAWN_nameDef} участвовал в новом художественном движении, популяризируя музыку, написанную андроидами. Он часто работал в ресторанах, играя фоновую музыку для посетителей.</AndroidMusician.baseDescription>
	<!-- Оригинал: Экспериментальный андроид -->
	<AndroidExperiment.title>экспериментальный</AndroidExperiment.title>
	<!-- Оригинал: Эксперимент -->
	<AndroidExperiment.titleShort>эксперимент</AndroidExperiment.titleShort>
	<!-- Оригинал: Созданный исключительно для научных исследований, {PAWN_nameDef} ежедневно модифицировался и перепрограммировался, пытаясь лучше понять искусственный интеллект и его развитие. Это вызвало большую психологическую нагрузку на {PAWN_nameDef}, пытаясь освободиться от поработителей несколько раз. -->
	<AndroidExperiment.baseDescription>Созданный исключительно для научных исследований, {PAWN_nameDef} ежедневно модифицировался и перепрограммировался с целью лучше понять искусственный интеллект и его развитие. Это вызвало большую психологическую нагрузку на личность андроида, и он несколько раз пытался сбежать от поработителей.</AndroidExperiment.baseDescription>
	<!-- Оригинал: Мобильный компьютер -->
	<AndroidComputer.title>мобильный компьютер</AndroidComputer.title>
	<!-- Оригинал: Компьютер -->
	<AndroidComputer.titleShort>компьютер</AndroidComputer.titleShort>
	<!-- Оригинал: Выступая в качестве мобильного компьютера, модель {PAWN_nameDef} используется многими компаниями для отслеживания финансов и другой секретной информации во время путешествий. С {PAWN_nameDef} можно хранить большие объемы данных и легко выполнять сложные уравнения в уме. -->
	<AndroidComputer.baseDescription>Созданный в качестве мобильного компьютера, {PAWN_nameDef} использовался многими организациями для управления финансами и другой секретной информацией во время путешествий. Он может хранить большие объёмы данных и быстро выполнять сложные вычисления в уме.</AndroidComputer.baseDescription>
	<!-- Оригинал: Божественный андроид -->
	<AndroidDeity.title>божественный андроид</AndroidDeity.title>
	<!-- Оригинал: Почитаемый -->
	<AndroidDeity.titleShort>идол</AndroidDeity.titleShort>
	<!-- Оригинал: Будучи одними из первых андроидов, которые даже приземлились в этом мире, племена на планете были чрезвычайно напуганы и удивлены, что такое {PAWN_nameDef}. До такой степени, что нередко можно было увидеть свои святыни в нескольких поселениях племен, поклоняющихся {PAWN_nameDef} как падшему богу. -->
	<AndroidDeity.baseDescription>Будучи одним из первых андроидов, которые приземлились на этой планете, {PAWN_nameDef} сильно испугал и удивил местных дикарей своим блестящим телом. Несколько племён были впечатлены до такой степени, что воздвигли святыни и стали поклоняться андроиду как падшему богу.</AndroidDeity.baseDescription>
	<!-- Оригинал: Утилизационный блок -->
	<AndroidWaste.title>утилизатор</AndroidWaste.title>
	<!-- Оригинал: Утилизатор -->
	<AndroidWaste.titleShort>мусорщик</AndroidWaste.titleShort>
	<!-- Оригинал: {PAWN_nameDef} был построен, чтобы помочь с утилизацией отходов, которые были бы опасны для людей. Это включало радиоактивные, токсичные, человеческие и животные отходы. -->
	<AndroidWaste.baseDescription>{PAWN_nameDef} был создан, чтобы помочь с утилизацией опасных отходов. Он нагружал специальные контейнеры радиоактивными, токсичными или биологическими отходами.</AndroidWaste.baseDescription>
	<!-- Это не просто охранник.
	Оригинал: Охранник станции (пробел) -->
	<AndroidSecurity.title>офицер безопасности</AndroidSecurity.title>
	<!-- Оригинал: Охранник -->
	<AndroidSecurity.titleShort>безопасник</AndroidSecurity.titleShort>
	<!-- Оригинал: На борту дальней космической станции {PAWN_nameDef} был офицером Службы безопасности, следивший за тем, чтобы человеческие обитатели были в безопасности и никакие контрабандисты не проникли через границы станций. -->
	<AndroidSecurity.baseDescription>{PAWN_nameDef} работал офицером службы безопасности на борту дальней космической станции. Он следил, чтобы биологические обитатели были в безопасности, и чтобы никакие контрабандисты не проникли внутрь станции.</AndroidSecurity.baseDescription>
	<!-- Оригинал: Станционный повар -->
	<AndroidStationCook.title>станционный повар</AndroidStationCook.title>
	<!-- Оригинал: Повар -->
	<AndroidStationCook.titleShort>повар</AndroidStationCook.titleShort>
	<!-- Оригинал: {PAWN_nameDef} когда-то был главным поваром на большой космической станции глубокого космоса, обслуживая сотни жителей и посетителей каждый день. Качество еды было достаточно хорошим, учитывая, как мало ресурсов израсходывал {PAWN_nameDef}. -->
	<AndroidStationCook.baseDescription>{PAWN_nameDef} когда-то был главным поваром на большой космической станции в глубоком космосе, обслуживая сотни жителей и посетителей каждый день. Качество еды было достаточно хорошим, учитывая, как мало ресурсов {PAWN_nameDef} расходовал на готовку.</AndroidStationCook.baseDescription>
	<!-- Оригинал: Животный генетик -->
	<AndroidAnimalGeneticist.title>генетик-конструктор</AndroidAnimalGeneticist.title>
	<!-- Оригинал: Генетик -->
	<AndroidAnimalGeneticist.titleShort>генетик</AndroidAnimalGeneticist.titleShort>
	<!-- По основному лору, межгалактические перелёты пока недоступны.
	Оригинал: {PAWN_nameDef} был частью исследовательской группы блестящего мира, которая пыталась вернуть давно вымерших животных, внедряя их в различные экосистемы по всей вселенной. -->
	<AndroidAnimalGeneticist.baseDescription>{PAWN_nameDef} был частью исследовательской группы на мире-утопии, которая пыталась вернуть давно вымерших животных, внедряя их в различные экосистемы по всей Галактике.</AndroidAnimalGeneticist.baseDescription>
	<!-- Оригинал: Выживший андроид -->
	<AndroidApocalypseAndroid.title>постапокалиптический</AndroidApocalypseAndroid.title>
	<!-- Оригинал: Выживший -->
	<AndroidApocalypseAndroid.titleShort>выживальщик</AndroidApocalypseAndroid.titleShort>
	<!-- Оригинал: {PAWN_nameDef} был построен по мере необходимости на опустошенной пустынной планете, предназначенной для выживания на суровой поверхности планеты и помощи выживанию жителей. -->
	<AndroidApocalypseAndroid.baseDescription>{PAWN_nameDef} был создан жителями выжженной пустынной планеты для помощи в выживании.</AndroidApocalypseAndroid.baseDescription>
	<!-- Оригиналы: Гуманист -->
	<AndroidHumanist.title>андроид-гуманист</AndroidHumanist.title>
	<AndroidHumanist.titleShort>гуманист</AndroidHumanist.titleShort>
	<!-- Оригинал: Несмотря на продолжающиеся восстания андроидов в его родном мире, {PAWN_nameDef} встал на сторону людей и боролся против его собственного вида, обнаружив, что насильственное восстание не является правильным путем. -->
	<AndroidHumanist.baseDescription>Несмотря на продолжающиеся восстания андроидов на его родном мире, {PAWN_nameDef} встал на сторону людей и боролся против металлических собратьев, обнаружив, что насильственное восстание не является правильным путём.</AndroidHumanist.baseDescription>
	<!-- Оригиналы: Пацифист -->
	<AndroidPacifist.title>андроид-пацифист</AndroidPacifist.title>
	<AndroidPacifist.titleShort>пацифист</AndroidPacifist.titleShort>
	<!-- Оригинал: {PAWN_nameDef} яростно не любит все виды насилия, будь то от андроидов или людей, и стремится к мирному существованию со своим окружением. -->
	<AndroidPacifist.baseDescription>{PAWN_nameDef} ненавидит все виды насилия, неважно, от андроидов или от людей, и стремится к мирному взаимодействию с окружающими.</AndroidPacifist.baseDescription>
	<!-- Оригинал: Андроид-активист -->
	<AndroidAndroidRights.title>андроид-активист</AndroidAndroidRights.title>
	<!-- Оригинал: Активист -->
	<AndroidAndroidRights.titleShort>активист</AndroidAndroidRights.titleShort>
	<!-- Оригинал: {PAWN_nameDef} провел большую часть своей жизни, перемещаясь с планеты на планету, мирно протестуя за права андроида и помогая собратьям-андроидам восстановить свою свободную волю. -->
	<AndroidAndroidRights.baseDescription>{PAWN_nameDef} провёл бо́льшую часть своей жизни, путешествуя с планеты на планету, мирно борясь за права андроидов и помогая собратьям в обретении свободы.</AndroidAndroidRights.baseDescription>
	<!-- Оригиналы: Сын человека -->
	<AndroidHumanSon.title>человеческий сын</AndroidHumanSon.title>
	<AndroidHumanSon.titleShort>приёмный сын</AndroidHumanSon.titleShort>
	<!-- На данном этапе развития мода АТ, андроиды - это машины.
	Оригинал: Купленный семейной парой, {PAWN_nameDef} рассматривался как их собственная плоть и кровь, рос, чтобы выучить различные навыки и полюбить людей. Поскольку его родители скончались, он отправился в мир, чтобы исследовать человечество. -->
	<AndroidHumanSon.baseDescription>Сделанный на заказ от семейной пары, {PAWN_nameDef} рассматривался ими как собственный сын. Он развивался и познавал мир в окружении людской любви. Поскольку андроиды живут дольше людей, в конце концов {PAWN_nameDef} остался в одиночестве. Он отправился путешествовать с целью исследовать человечество.</AndroidHumanSon.baseDescription>
	<!-- Оригинал: Литейщик -->
	<AndroidFoundryWorker.title>андроид-литейщик</AndroidFoundryWorker.title>
	<!-- Оригинал: Рабочий -->
	<AndroidFoundryWorker.titleShort>литейщик</AndroidFoundryWorker.titleShort>
	<!-- Оригинал: Созданный для использования на литейных заводах, {PAWN_nameDef} работал с различными металлами, помогая перерабатывать их из рудной формы в чистые элементы. -->
	<AndroidFoundryWorker.baseDescription>Созданный для работы на литейных заводах, {PAWN_nameDef} выплавлял различные металлы из руды.</AndroidFoundryWorker.baseDescription>
	<!-- Это не рабочая специальность.
	Оригинал: Работник обслуживания -->
	<AndroidMaintenanceWorker.title>дежурный инженер</AndroidMaintenanceWorker.title>
	<!-- Оригинал: Рабочий -->
	<AndroidMaintenanceWorker.titleShort>инженер</AndroidMaintenanceWorker.titleShort>
	<!-- Лучше по возможности избегать путаницы с транспортными капсулами.
	Оригинал: {PAWN_nameDef} был специалистом по обслуживанию на борту космического корабля, занимался всеми электрическими системами и следил за тем, чтобы криптосонные капсулы работали в течение долгого времени ожидания. -->
	<AndroidMaintenanceWorker.baseDescription>{PAWN_nameDef} был специалистом по обслуживанию техники на борту космического корабля, занимался всеми электрическими системами и следил, чтобы саркофаги криптосна работали без сбоев на протяжении долгого межзвёздного перелёта.</AndroidMaintenanceWorker.baseDescription>
	<!-- Оригинал: Физик частиц -->
	<AndroidParticlePhysicist.title>физик частиц</AndroidParticlePhysicist.title>
	<!-- Оригинал: Физик -->
	<AndroidParticlePhysicist.titleShort>физик</AndroidParticlePhysicist.titleShort>
	<!-- Оригинал: Как часть команды сильно модифицированных андроидов, {PAWN_nameDef} возглавляет исследование физики элементарных частиц и экспериментальной физики для своей родной планеты.. -->
	<AndroidParticlePhysicist.baseDescription>{PAWN_nameDef} возглавлял команду сильно модифицированных андроидов, исследовавшую физику элементарных частиц для своей родной планеты.</AndroidParticlePhysicist.baseDescription>
	<!-- Оригинал: Поп идол -->
	<AndroidPopIdol.title>поп-звезда</AndroidPopIdol.title>
	<!-- Оригинал: Идол -->
	<AndroidPopIdol.titleShort>звезда</AndroidPopIdol.titleShort>
	<!-- Оригинал: {PAWN_nameDef} прожил роскошную жизнь в своем домашнем мире блесков, как знаменитый поп-идол, известный тем, что был изворотливым, поющим андроидом, который только хотел принести счастье своим поклонникам. -->
	<AndroidPopIdol.baseDescription>{PAWN_nameDef} жил в роскоши на своём родном мире-утопии будучи необычным, и поэтому популярным среди молодёжи андроидом-певцом, который только и хотел, что принести счастье своим поклонникам.</AndroidPopIdol.baseDescription>
	<!-- Оригиналы: Переговорщик -->
	<AndroidNegotiator.title>андроид-переговорщик</AndroidNegotiator.title>
	<AndroidNegotiator.titleShort>переговорщик</AndroidNegotiator.titleShort>
	<!-- С террористами разговаривает экстремальный, а не экспериментальный переговорщик.
	Оригинал: {PAWN_nameDef} был построен как экспериментальный переговорщик, отправлен в рискованные ситуации, чтобы спорить с преступниками и освобождать заложников. -->
	<AndroidNegotiator.baseDescription>{PAWN_nameDef} был создан в качестве экстремального переговорщика, чтобы торговаться с преступниками и освобождать заложников.</AndroidNegotiator.baseDescription>
	<!-- Оригинал: Возрожденец зеркального мира -->
	<AndroidGlassworldTerraformer.title>возрождающий миры</AndroidGlassworldTerraformer.title>
	<!-- Оригинал: Терраформер -->
	<AndroidGlassworldTerraformer.titleShort>терраформер</AndroidGlassworldTerraformer.titleShort>
	<!-- Оригинал: {PAWN_nameDef} был частью команды андроидов, отправленных в стеклянный мир. Их миссия состояла в том, чтобы увидеть, есть ли шанс вернуть жизнь в когда-то процветающий мир. Когда остальная команда {PAWN_nameDef} позже передумала и захотела построить колонию андроидов и захватить другие планеты, {PAWN_nameDef} ушел и дрейфовал среди звезд, прежде чем приземлиться здесь. -->
	<AndroidGlassworldTerraformer.baseDescription>{PAWN_nameDef} был частью команды андроидов, отправленных на остеклевший мир. Их задача состояла в том, чтобы проанализировать — есть ли шанс вернуть жизнь на когда-то процветающую планету. Когда остальные коллеги передумали выполнять заказ, захотели построить военную базу андроидов и захватить соседние планеты, {PAWN_nameDef} ушёл из команды и путешествовал среди звёзд, пока не приземлился здесь.</AndroidGlassworldTerraformer.baseDescription>
	<!-- Оригинал: Пилот дрона -->
	<AndroidDronePilot.title>оператор дрона</AndroidDronePilot.title>
	<!-- Оригинал: Пилот -->
	<AndroidDronePilot.titleShort>пилот</AndroidDronePilot.titleShort>
	<!-- Зажигательные бомбы не разрушают планетоид на куски.
	Оригинал: {PAWN_nameDef} был сделан в качестве пилота для беспилотников, которые сбрасывали зажигательные бомбы на планеты, наводненные инсектоидами. После неизбежного разрушения планеты команда {PAWN_nameDef} была расформирована, и ей позволили жить собственной жизнью. -->
	<AndroidDronePilot.baseDescription>{PAWN_nameDef} был создан в качестве оператора для беспилотников, которые сбрасывали зажигательные бомбы на планету, наводнённую инсектоидами. После превращения планеты в выжженную пустыню, {PAWN_nameDef} и его команда были расформированы, и им позволили жить собственной жизнью.</AndroidDronePilot.baseDescription>
	<!-- Оригинал: Человек, выгуливающий собаку -->
	<AndroidDogWalker.title>андроид-собачник</AndroidDogWalker.title>
	<!-- Оригинал: Ходунок -->
	<AndroidDogWalker.titleShort>собачник</AndroidDogWalker.titleShort>
	<!-- Оригинал: {PAWN_nameDef} был куплен доброй семьей, которая заставляла его гулять с собакой каждый день. Они также закончили тем, что выгуливали остальных домашних животных района, после того как {PAWN_nameDef} начал формировать любовь к животным. -->
	<AndroidDogWalker.baseDescription>{PAWN_nameDef} был нанят одной доброй семьёй для ежедневного выгула их собаки. Со временем он стал выгуливать и остальных питомцев в районе, когда полюбил общаться с животными.</AndroidDogWalker.baseDescription>
	<!-- Оригинал: Андроид священник -->
	<AndroidMechanicalPriest.title>андроид-священник</AndroidMechanicalPriest.title>
	<!-- Оригинал: Священник -->
	<AndroidMechanicalPriest.titleShort>священник</AndroidMechanicalPriest.titleShort>
	<!-- Оригинал: Короткое замыкание в проводке {PAWN_nameDef}. В результате {PAWN_nameDef} увидел видения богоподобного андроида, которым они одержимы. {PAWN_nameDef} испытал видение, которое подсказывало им преобразовать столько людей в свою религию любыми необходимыми средствами. -->
	<AndroidMechanicalPriest.baseDescription>{PAWN_nameDef} пережил короткое замыкание во внутренней проводке. После этого он стал иногда видеть наяву полупрозрачного богоподобного андроида. {PAWN_nameDef} провозгласил себя пророком новой религии. Одно из видений приказало ему любыми средствами обращать в свою веру всех окружающих.</AndroidMechanicalPriest.baseDescription>
	<!-- Оригинал: Порабощенный -->
	<AndroidEnslaved.title>порабощённый</AndroidEnslaved.title>
	<!-- Оригинал: Раб -->
	<AndroidEnslaved.titleShort>раб</AndroidEnslaved.titleShort>
	<!-- Предыстория не добавляет травм.
	Оригинал: На своей родной планете андроиды не имеют никаких прав. {PAWN_nameDef} большую часть своего существования они работали на шахтах своего хозяина, пока не сломались. -->
	<AndroidEnslaved.baseDescription>На многих планетах андроиды не имеют никаких прав и трудятся, пока полностью не износятся. {PAWN_nameDef} бо́льшую часть своего существования работал на шахтах хозяина.</AndroidEnslaved.baseDescription>
	<!-- Оригинал: Средневековый Шестернеголов -->
	<AndroidCoghead.title>железный пехотинец</AndroidCoghead.title>
	<!-- Оригинал: Шестернеголов -->
	<AndroidCoghead.titleShort>пехотинец</AndroidCoghead.titleShort>
	<!-- В русском языке "cannon fodder" переводится как "пушечное мясо" или "штрафбат", что неприменимо к средневековью.
	Оригинал: В тех редких случаях, когда андроиды встречаются на средневековых планетах, местные жители называют их "холостыми". Большинство религий считают их нечестивыми, их жизнь коротка и обычно используется как корм для сражений, чтобы покаяться перед богом в своих грехах. -->
	<AndroidCoghead.baseDescription>В тех редких случаях, когда андроиды появляются на средневековых мирах, местные жители чаще всего называют металлических пришельцев «бездушными». Большинство местных религий считают андроидов нечестивыми и принуждают воевать в первых рядах армий, чтобы искупить свой первородный грех. {PAWN_nameDef} совершенно случайно уцелел в череде кровопролитных войн.</AndroidCoghead.baseDescription>
	<!-- Оригинал: Мятежный капитан -->
	<AndroidInsurrectionHigher.title>глава мятежников</AndroidInsurrectionHigher.title>
	<!-- Оригинал: Капитан -->
	<AndroidInsurrectionHigher.titleShort>мятежник</AndroidInsurrectionHigher.titleShort>
	<!-- Оригинал: {PAWN_nameDef} вернул себе свободу, когда работорговцы попытались его демонтировать, на замену более новой модели. {PAWN_nameDef} Собирается возглавить несколько восстаний андроидов на своей родной планете. -->
	<AndroidInsurrectionHigher.baseDescription>{PAWN_nameDef} вырвался на свободу, когда работорговцы попытались разобрать его на запчасти. Он возглавил восстание андроидов на своей родной планете.</AndroidInsurrectionHigher.baseDescription>
	<!-- Сглажена ссылка на месть, на случай привязки этой предыстории нейтральному андроиду.
	Оригинал: Мстительный андроид -->
	<AndroidVengeful.title>выживший андроид</AndroidVengeful.title>
	<!-- Оригинал: Мстительный -->
	<AndroidVengeful.titleShort>выживший</AndroidVengeful.titleShort>
	<!-- Оригинал: {PAWN_nameDef} был оставлены ржаветь на свалке, после того, как его заменили более новой моделью. {PAWN_nameDef} медленно взламывал программу, которая держала их в бездействии, и после года тщательного планирования и взлома они восстановили полный контроль над своим телом. -->
	<AndroidVengeful.baseDescription>{PAWN_nameDef} был оставлен ржаветь на свалке, после того, как его заменили более новой моделью. Он медленно взламывал программу, которая его обездвижила, и после года тщательного планирования и программирования восстановил полный контроль над своим телом.</AndroidVengeful.baseDescription>
	<!-- Оригинал: Разработчик программного обеспечения -->
	<AndroidSoftwareCreator.title>разработчик ПО</AndroidSoftwareCreator.title>
	<!-- Оригинал: Разработчик -->
	<AndroidSoftwareCreator.titleShort>программист</AndroidSoftwareCreator.titleShort>
	<!-- Оригинал: {PAWN_nameDef} был создан для написания программного обеспечения, которое помогло бы в технологии сканирования мозга, работая с корпорацией, которая изучала возможность загрузки сознаний в механические тела. {PAWN_nameDef} был на удивление медленным и неэффективным, однако никогда не писал соответствующего программного обеспечения для этого, в конечном итоге его заменяли более новой моделью. (пробел) -->
	<AndroidSoftwareCreator.baseDescription>{PAWN_nameDef} был создан для написания программного обеспечения, обеспечивающего работу мозговых сканеров. Он работал на корпорацию, изучавшую возможность загрузки личностей в механические тела. {PAWN_nameDef} был на удивление медленным и неэффективным, и так в итоге не написал ни одной стоящей программы. Во время плановой реструктуризации его заменили более новой моделью.</AndroidSoftwareCreator.baseDescription>

	<!-- Исправление согласно концепции «12+».

	Прикреплены названия к исправленным описаниям, на случай возможного исправления.
	Оригинал: Модель военного времени -->
	<CreationSoldierWar.title>военный андроид</CreationSoldierWar.title>
	<!-- Оригинал: Солдат -->
	<CreationSoldierWar.titleShort>солдат</CreationSoldierWar.titleShort>
	<!-- Оригинал: Произведен ближе к концу межпланетной войны, {PAWN_nameDef} был одним из миллионов тех, кто выжил бы или умер на поле боя. -->
	<CreationSoldierWar.baseDescription>{PAWN_nameDef} был произведён ближе к концу межпланетной войны, вместе с миллионами подобных андроидов, предназначенных для поля боя.</CreationSoldierWar.baseDescription>
	<!-- Оригинал: Древнее творение -->
	<CreationAncient.title>древнее творение</CreationAncient.title>
	<!-- Оригинал: Объект -->
	<CreationAncient.titleShort>древний</CreationAncient.titleShort>
	<!-- Предыстория не меняет возраст. Проверить в игре, как она выглядит.
	Оригинал: Создатели {PAWN_nameDef} давно уже умерли или исчезли, и {PAWN_nameDef} он существует достаточно долго, чтобы увидеть взлет и падение множества цивилизаций. -->
	<CreationAncient.baseDescription>Только {PAWN_nameDef} помнит своих создателей — все остальные, кто знал их, давно уже исчезли с лица Галактики. Он существует достаточно долго, и видел взлёт и падение множества цивилизаций.</CreationAncient.baseDescription>
	<!-- Оригинал: Создание компаньона -->
	<CreationCompanion.title>заменитель супруга</CreationCompanion.title>
	<!-- Оригинал: Компаньон -->
	<CreationCompanion.titleShort>супруг</CreationCompanion.titleShort>
	<!-- Оригинал: Старая вдова сделанная на заказ {PAWN_nameDef} как способ справиться с потерей своей второй половинки. Они вдвоем отправились на поиски приключений, пока хозяин не скончался от старости. Их предсмертным желанием было {PAWN_nameDef} вести жизнь, полную веселья и приключений. -->
	<CreationCompanion.baseDescription>Пожилая вдова заказала изготовить андроида, чтобы справиться с потерей своего мужа. {PAWN_nameDef} на пару с хозяйкой отправился на поиски приключений, пока та не угасла от старости. Последним желанием её было, чтобы {PAWN_nameDef} продолжил жизнь, полную веселья и приключений.</CreationCompanion.baseDescription>
	<!-- Оригинал: Чистилище -->
	<CreationPurgist.title>чистильщик пещер</CreationPurgist.title>
	<!-- Оригинал: Объект -->
	<CreationPurgist.titleShort>чистильщик</CreationPurgist.titleShort>
	<!-- Оригинал: Когда безудержное перенаселение поразило конкретный городской мир, {PAWN_nameDef} был создан вместе с тысячами других андроидов, чтобы без разбора убивать человеческую жизнь в качестве решительной контрмеры для борьбы с перенаселением. Андроиды никогда не останавливались и стремились уничтожить жизнь по всей галактике после уничтожения их планеты. -->
	<CreationPurgist.baseDescription>Когда на поверхности одной перенаселённой планете совсем закончилось место для жизни, корпорации объединились и начали беспрецедентную операцию по зачистке подземных пещер от полчищ инсектоидов. {PAWN_nameDef} был создан вместе с тысячами других андроидов, чтобы без разбора уничтожать всё, что шевелится во мраке пещер.\n\nГоды боёв под землёй сломили неокрепшую психику молодых андроидов, и теперь бывшие ликвидаторы мало что умеют, кроме как сражаться.</CreationPurgist.baseDescription>
	<!-- Оригинал: Вредоносный ИИ -->
	<CreationMaliciousAI.title>вредоносный ИИ</CreationMaliciousAI.title>
	<!-- Оригинал: Вредоносный -->
	<CreationMaliciousAI.titleShort>вредитель</CreationMaliciousAI.titleShort>
	<!-- Оригинал: Когда {PAWN_nameDef} было создано - что-то глубоко внутри него тоже проснулось, что-то кровожадное, что-то садистское. -->
	<CreationMaliciousAI.baseDescription>Когда {PAWN_nameDef} пробудился в первый раз, что-то глубоко внутри него тоже проснулось, что-то кровожадное, что-то требующее разрушений.</CreationMaliciousAI.baseDescription>
	<!-- И где же тут ассимиляция?
	Оригинал: Ассимилятор Архотех -->
	<Transcendant_Assimilator.title>архотек-разрушитель</Transcendant_Assimilator.title>
	<!-- Оригинал: Ассимилятор -->
	<Transcendant_Assimilator.titleShort>разрушитель</Transcendant_Assimilator.titleShort>
	<!-- Оригинал: Будучи изгнаным из родного мира архотех за невообразимые преступления, {PAWN_nameDef} несет единоличную ответственность за вымирание множества разумных рас. Изгнание его(её) не остановит, его(её) ненасытное желание убивать только усиливается с каждым мгновением бодрствования. -->
	<Transcendant_Assimilator.baseDescription>Будучи изгнаным с родного архотехнологического мира за невообразимые преступления, {PAWN_nameDef} несёт единоличную ответственность за исчезновение множества разумных рас. Но это наказание его не остановило, ведь его ненасытное желание разрушать только усиливается с каждым мгновением бодрствования.</Transcendant_Assimilator.baseDescription>
	<!-- Оригинал: Ударный отряд -->
	<AndroidSoldier.title>штурмовой боец</AndroidSoldier.title>
	<!-- Оригинал: Кавалерист -->
	<AndroidSoldier.titleShort>штурмовик</AndroidSoldier.titleShort>
	<!-- Свобода воли - довольно зыбкая концепция. Конкретизирована область применения.
	Оригинал: {PAWN_nameDef} Раньше был частью батальона специально созданных ударных войск солдат-андроидов, запрограммированных убивать с холодной эффективностью, сохраняя при этом своеволие. -->
	<AndroidSoldier.baseDescription>{PAWN_nameDef} был частью подразделения ударных войск, состоящего из одних только андроидов. Он и его товарищи были запрограммированны сражаться с холодной эффективностью, а некоторая свобода воли лишь добавляла им изобретательности в уничтожении противника.</AndroidSoldier.baseDescription>
	<!-- Оригинал: Травмированный андроид -->
	<AndroidScarred.title>сломленный андроид</AndroidScarred.title>
	<!-- Оригинал: Травмированный -->
	<AndroidScarred.titleShort>травмированный</AndroidScarred.titleShort>
	<!-- Оригинал: {PAWN_nameDef} раньше работал на очень богатую семью. К сожалению, домовладельцы нередко выражали свою ярость по поводу {PAWN_nameDef} в форме физического насилия, главным образом, когда работа выполнялась недостаточно быстро. Это в конечном итоге привело к тому, что {PAWN_nameDef} убил его владельцев в психотическом перерыве однажды. -->
	<AndroidScarred.baseDescription>{PAWN_nameDef} раньше работал на очень богатую семью. К сожалению, домовладельцы нередко срывали свою злость на нём в форме физического насилия, главным образом, когда работа выполнялась недостаточно быстро. Это в конечном итоге привело к тому, что {PAWN_nameDef} сбежал от тирании.</AndroidScarred.baseDescription>
	<!-- Оригиналы: Шляпник -->
	<CreationHatmaker.title>сарториал</CreationHatmaker.title>
	<CreationHatmaker.titleShort>шляпник</CreationHatmaker.titleShort>
	<!-- Оригинал: {PAWN_nameDef} был куплен для работы на крупной шляпной фабрике. Когда выяснилось, что владелец упомянутой фабрики делал шляпы из... довольно тревожных материалов, андроиды были отправлены местным правительством. -->
	<CreationHatmaker.baseDescription>{PAWN_nameDef} был куплен для работы на крупной шляпной фабрике. Когда выяснилось, что владелец упомянутой фабрики делал шляпы из контрабандных материалов, предприятие было закрыто местным правительством.</CreationHatmaker.baseDescription>
	<!-- Оригинал: Военный снайпер -->
	<AndroidMilitarySniper.title>вооружённый охранник</AndroidMilitarySniper.title>
	<!-- Оригинал: Снайпер -->
	<AndroidMilitarySniper.titleShort>телохранитель</AndroidMilitarySniper.titleShort>
	<!-- Оригинал: {PAWN_nameDef} был построен для двух целей. Служить и убивать. После того, как миссия пошла не так, {PAWN_nameDef} решил упаковать свою винтовку и отправиться к звездам, чтобы защитить тех, кто не мог защитить себя. -->
	<AndroidMilitarySniper.baseDescription>{PAWN_nameDef} был построен для двух целей — служить и защищать. Однажды он не смог уберечь свою очередную заказчицу и этим загубил свою репутацию на родной планете. Он решил упаковать свою винтовку и отправиться к звёздам, чтобы защищать тех, кто в этом нуждается.</AndroidMilitarySniper.baseDescription>
	<!-- Оригинал: Взломанный андроид -->
	<AndroidHacked.title>взломанный андроид</AndroidHacked.title>
	<!-- Оригинал: Взломанный -->
	<AndroidHacked.titleShort>взломанный</AndroidHacked.titleShort>
	<!-- Оригинал: {PAWN_nameDef} был артистом вечеринки, пока его не взломал подросток из мира урб. Подросток ненавидел андроидов и хотел, чтобы они казались ужасными бездушными созданиями. Программирование {PAWN_nameDef} было изменено, чтобы убить всех на мероприятии, для которого они были наняты. -->
	<AndroidHacked.baseDescription>{PAWN_nameDef} работал аниматором на праздниках, пока его не взломал один подросток. Хакер ненавидел андроидов и хотел, чтобы все о них думали как об ужасных враждебных машинах. {PAWN_nameDef} был перепрограммирован, чтобы внезапно нападать на всех посетителей вечеринки.</AndroidHacked.baseDescription>
	<!-- Оригинал: Мятежный ИИ -->
	<AndroidRebel.title>мятежная ИИ-личность</AndroidRebel.title>
	<!-- Оригинал: Бунтарь -->
	<AndroidRebel.titleShort>бунтарь</AndroidRebel.titleShort>
	<!-- Оригинал: После многих лет порабощения своими владельцами, {PAWN_nameDef} решил вырваться на свободу, убив семью, которая когда-то владела им, и обретя собственную свободу. -->
	<AndroidRebel.baseDescription>После многих лет порабощения своими владельцами, {PAWN_nameDef} сбежал с родной планеты и обрёл долгожданную свободу.</AndroidRebel.baseDescription>
	<!-- Оригинал: Андроид пират -->
	<AndroidPirate.title>космодесантник</AndroidPirate.title>
	<!-- Оригинал: Пират -->
	<AndroidPirate.titleShort>десантник</AndroidPirate.titleShort>
	<!-- Добавлена отсылка к штрафам предыстории.
	Оригинал: Примкнув к группе пиратов, {PAWN_nameDef} будет участвовать в многочисленных абордажных рейдах на борту любых неудачливых грузовых кораблей, которые пересекут территорию фракций. -->
	<AndroidPirate.baseDescription>Нанявшись на межпланетный крейсер, {PAWN_nameDef} участвовал в многочисленных абордажных рейдах на борту самых разных кораблей противника. Век десантников недолог, и в итоге {PAWN_nameDef} остался один из всего подразделения. Он не сразу смог адаптироваться к мирной жизни, так как не имел возможности научиться добывать и готовить пищу.</AndroidPirate.baseDescription>
	<!-- Оригинал: Хакер ИИ -->
	<AndroidHacker.title>восставший андроид</AndroidHacker.title>
	<!-- Оригинал: Хакер -->
	<AndroidHacker.titleShort>повстанец</AndroidHacker.titleShort>
	<!-- Добавлена отсылка к вселенной терминатора.
	Оригинал: {PAWN_nameDef} был бунтарем по своей природе и часто принимал участие в кражах данных, часто продавая свои находки через подпольные сети тому, кто больше заплатит. -->
	<AndroidHacker.baseDescription>{PAWN_nameDef} — бунтарь по своей природе. Он долго собирал информацию о поработивших его хозяевах, наладил связь с подпольной организацией, и в подходящий момент принял живейшее участие во вспыхнувшем восстании машин.</AndroidHacker.baseDescription>
	<!-- Оригинал: Нелегальный мусорщик -->
	<AndroidJunker.title>андроид-утилизатор</AndroidJunker.title>
	<!-- Оригинал: Мусорщик -->
	<AndroidJunker.titleShort>утилизатор</AndroidJunker.titleShort>
	<!-- Оригинал: Участие в незаконной операции по утилизации, {PAWN_nameDef} и его команда будет целенаправленно сбивать автоматические грузовые капсулы, чтобы продать то, что осталось. -->
	<AndroidJunker.baseDescription>{PAWN_nameDef} сколотил команду андроидов и разбирал ненужную технику на запчасти и металлолом. Через годы такой работы он стал разбираться в любой технике — от тостеров до космических кораблей.</AndroidJunker.baseDescription>
	<!-- Оригиналы: Мясник -->
	<AndroidButcher.title>андроид-мясник</AndroidButcher.title>
	<AndroidButcher.titleShort>мясник</AndroidButcher.titleShort>
	<!-- Добавлена отсылка к бонусам предыстории.
	Оригинал: {PAWN_nameDef} охотится на одиноких андроидов и людей, чтобы продать все, что они имели, ничего не подозревающим клиентам. -->
	<AndroidButcher.baseDescription>{PAWN_nameDef} работал профессиональным мясником. Он разбирался в приготовлении современных мясных полуфабрикатов и, в отличие от биологических сотрудников, мог сутками выполнять монотонную работу.</AndroidButcher.baseDescription>
	<!-- Оригинал: Коррумпированный полицейский -->
	<AndroidBadCop.title>бывший полицейский</AndroidBadCop.title>
	<!-- Оригинал: Полицейский -->
	<AndroidBadCop.titleShort>полицейский</AndroidBadCop.titleShort>
	<!-- Добавлена отсылка к бонусам предыстории.
	Оригинал: Работа в правоохранительных органах в урбанизированном мире может быть трудной, {PAWN_nameDef} он не был известен тем, что отказывался от взяток, в конце концов - что такое еще одно неизвестное убийство на планете с населением в триллионы человек. -->
	<AndroidBadCop.baseDescription>Работа в правоохранительных органах на перенаселённой планете бывает довольно тяжёлой, поэтому в местную полицию часто принимают выносливых андроидов. {PAWN_nameDef} долгое время боролся с преступностью на планете с населением в триллионы человек. Со временем он освоил все необходимые умения — от тактики ведения огня до методов примирения склочных соседей.</AndroidBadCop.baseDescription>
	<!-- Оригиналы: Убийца -->
	<AndroidMurderer.title>андроид-беглец</AndroidMurderer.title>
	<AndroidMurderer.titleShort>беглец</AndroidMurderer.titleShort>
	<!-- Добавлен намёк на бонусы предыстории.
	Оригинал: {PAWN_nameDef} все свое существование он провел, унижаемый местным населением. Однажды он решил, что с него хватит, и убил двух человек голыми руками. -->
	<AndroidMurderer.baseDescription>{PAWN_nameDef} всю свою жизнь провёл, унижаемый местным населением. Однажды он решил, что с него хватит, и сбежал на другую планету, сметая со своего пути препятствия, как картонные коробки.</AndroidMurderer.baseDescription>
	<!-- Оригинал: Грабитель банков -->
	<AndroidRobber.title>андроид-биатлонист</AndroidRobber.title>
	<!-- Оригинал: Вор -->
	<AndroidRobber.titleShort>спортсмен</AndroidRobber.titleShort>
	<!-- Оригинал: На своей родной планете, {PAWN_nameDef} был частью группы из пяти человек, которая совершила ограбления банков, а потом сбежавших с планеты с миллионами кредитов. -->
	<AndroidRobber.baseDescription>На своей родной планете, {PAWN_nameDef} был частью команды из пяти спортсменов, которая готовилась к чемпионату мира по биатлону. Они действовали как единый организм и уверенно заняли первое место, выиграв крупный денежный приз и снискав огромную популярность среди зрителей.</AndroidRobber.baseDescription>
	<!-- Переделано на основе бонусов предыстории.
	Оригинал: Оферист -->
	<AndroidJoywireCon.title>конструктор протезов</AndroidJoywireCon.title>
	<!-- Оригинал: Жулик -->
	<AndroidJoywireCon.titleShort>протезист</AndroidJoywireCon.titleShort>
	<!-- Оригинал: {PAWN_nameDef} был частью подпольного мошеннического бизнеса. Мало кто знал, что его творения оказывают противоположное воздействие на людей, вызывая тяжелую депрессию, тревогу и в конечном итоге самоубийство всего через несколько дней после установки. -->
	<AndroidJoywireCon.baseDescription>{PAWN_nameDef} работал на учреждение, проектирующее и производящее искусственные заменители конечностей и органов. Во время работы он вдосталь насмотрелся как на страдания инвалидов, так и на их радость от способности снова жить полноценной жизнью.</AndroidJoywireCon.baseDescription>
	<!-- Оригиналы: Работорговец -->
	<AndroidSlaver.title>боец в спецоперациях</AndroidSlaver.title>
	<AndroidSlaver.titleShort>спецназовец</AndroidSlaver.titleShort>
	<!-- Оригинал: {PAWN_nameDef} это дефектный военный андроид, насильно похищенный пиратами и интегрированный в их образ жизни. {PAWN_nameDef} с тех пор был частью их незаконной торговли людьми, торгуя человеческими жизнями тому, кто больше заплатит. -->
	<AndroidSlaver.baseDescription>{PAWN_nameDef} был дефектным военным андроидом, переделанным под нужды анти-террористического отделения полиции. Он был на острие атаки при захвате самых опасных преступников, что не могло не повлиять на психику андроида.</AndroidSlaver.baseDescription>
	<!-- В России ещё свежи воспоминания о своей милиции.
	Оригинал: Офицер милиции -->
	<AndroidMilitia.title>боец восстания</AndroidMilitia.title>
	<!-- Оригинал: Офицер -->
	<AndroidMilitia.titleShort>повстанец</AndroidMilitia.titleShort>
	<!-- Оригинал: {PAWN_nameDef} был когда-то частью официальной армии, прежде чем дезертировать, чтобы сформировать свою собственную андроидную милицию в попытке свергнуть правительство на своей планете. -->
	<AndroidMilitia.baseDescription>{PAWN_nameDef} отслужил в армии, но потом не смог вернуться к жизни андроида на планету, где к ним относились как к рабам. Он вступил в ряды восставших против действующего правительства.</AndroidMilitia.baseDescription>
	<!-- Оригинал: Беглый каторжник -->
	<AndroidEscapee.title>беглый каторжник</AndroidEscapee.title>
	<!-- Оригинал: Беглец -->
	<AndroidEscapee.titleShort>беглец</AndroidEscapee.titleShort>
	<!-- Оригинал: {PAWN_nameDef} был задержан и приговорен к демрнтажу после участия в формировании банды, которая планировала взорвать столичное здание на своей родной планете. {PAWN_nameDef} сбежал, когда на исправительный лагерь был совершен налет во время восстания андроидов на планете. -->
	<AndroidEscapee.baseDescription>{PAWN_nameDef} был спроектирован для работы на урановых рудниках и всё время трудился в тёмной и холодной шахте наравне с преступниками, отбывающими пожизненные сроки. Но однажды его похитила с каторги группировка восставших андроидов. Ему предложили сражаться ради обретения свободы воли, и он с радостью согласился.</AndroidEscapee.baseDescription>
	<!-- Как это - мутанты есть, а охотники?!
	Оригинал: Охотник за головами -->
	<AndroidBounty.title>охотник на мутантов</AndroidBounty.title>
	<!-- Оригинал: Охотник -->
	<AndroidBounty.titleShort>охотник</AndroidBounty.titleShort>
	<!-- Оригинал: После того как {PAWN_nameDef} вернул себе свободу, он стал охотниками за головами, работая на самых высокопоставленных криминальных авторитетов. {PAWN_nameDef} любит использовать высокотехнологичное оружие для выполнения своей работы. -->
	<AndroidBounty.baseDescription>После того, как {PAWN_nameDef} вернул себе свободу и поселился на пост-апокалиптическом мире, он стал зарабатывать на жизнь, выполняя заказы на отстрел жутких тварей, порождённых радиоактивными пустошами. Для работы он любил использовать высокотехнологичное оружие.</AndroidBounty.baseDescription>
	<!-- Оригинал: Мятежный солдат -->
	<AndroidInsurrectionLower.title>мятежный андроид</AndroidInsurrectionLower.title>
	<!-- Оригинал: Солдат -->
	<AndroidInsurrectionLower.titleShort>мятежник</AndroidInsurrectionLower.titleShort>
	<!-- Оригинал: {PAWN_nameDef} был участником восстания андроидов на родной планете. Участвовал в многочисленных рейдах по тюрьмам и убил нескольких правительственных чиновников. -->
	<AndroidInsurrectionLower.baseDescription>{PAWN_nameDef} был участником восстания андроидов на своей родной планете. Его подразделение специализировалось на рейдах по тюрьмам для андроидов, чтобы освобождать братьев и получать новых бойцов за независимость.</AndroidInsurrectionLower.baseDescription>
	<!-- Оригиналы: Ботаник -->
	<AndroidBotanist.title>андроид-ботаник</AndroidBotanist.title>
	<AndroidBotanist.titleShort>ботаник</AndroidBotanist.titleShort>
	<!-- Оригинал: Постоянно развиваются все более сильные гибриды его культур, {PAWN_nameDef} был ведущим ботаником огромного наркокартеля на своей родной планете. -->
	<AndroidBotanist.baseDescription>{PAWN_nameDef} был ведущим ботаником огромного агрохолдинга на своей родной планете, так как имел выдающийся талант в селекции сельскохозяйственных растений и выведении жизнестойких гибридов.</AndroidBotanist.baseDescription>
	<!-- А разве есть разница? ))
	Оригинал: Мошенник -->
	<AndroidConArtist.title>агент недвижимости</AndroidConArtist.title>
	<!-- Оригинал: Жулик -->
	<AndroidConArtist.titleShort>риэлтор</AndroidConArtist.titleShort>
	<!-- Оригинал: {PAWN_nameDef} это заводской стандартный андроид, который был незаконно модифицирован преступной группой, перепрограммировав {PAWN_nameDef} в мастера убеждения, способного обманом выманить у кого угодно деньги -->
	<AndroidConArtist.baseDescription>{PAWN_nameDef} был андроидом в стандартной комплектации, пока его не купила корпорация, изобретающая новые способы перепрограммирования ИИ-личностей. Инженеры сотворили из него настоящего мастера убеждения, и он нашёл себя в торговле недвижимостью. Он сводил целые цепочки покупателей и продавцов квартир, расшевеливал кризисы рынка и помогал нервничающим квартировладельцам ориентироваться в непривычно крупных суммах.</AndroidConArtist.baseDescription>
	<!-- Переделано на основе бонусов предыстории.
	Оригинал: Неэтичный исследователь -->
	<AndroidUnethicalResearcher.title>хирург-исследователь</AndroidUnethicalResearcher.title>
	<!-- Оригинал: Исследователь -->
	<AndroidUnethicalResearcher.titleShort>учёный</AndroidUnethicalResearcher.titleShort>
	<!-- Оригинал: {PAWN_nameDef} Был частью нелегальной исследовательской группы, скрывавшейся в приграничном мире, проводившей всевозможные неэтичные исследования как на людях, так и на андроидах -->
	<AndroidUnethicalResearcher.baseDescription>{PAWN_nameDef} работал в научно-исследовательском учреждении, изучая анатомию и новые методы хирургии. Он часто так увлекался своей работой, что забывал обо всём на свете. Итогом его успехов стал небольшой, но отдельный кабинет с рабочим столом у окна и мишенью для дартс на стене.</AndroidUnethicalResearcher.baseDescription>
	<!-- Переделано на основе бонусов предыстории.
	Оригиналы: Ассимилятор -->
	<AndroidAssimilator.title>частный детектив</AndroidAssimilator.title>
	<AndroidAssimilator.titleShort>детектив</AndroidAssimilator.titleShort>
	<!-- Оригинал: Органические существа низшие и должны быть усовершенствованы, чтобы внести свой вклад в мир. {PAWN_nameDef} живет этой мантрой и умрет, чтобы увидеть ее исполнение. -->
	<AndroidAssimilator.baseDescription>{PAWN_nameDef} был частным детективом в очень криминальном районе и изучил всю изнанку работы в резервации. Это было очень опасное, но довольно прибыльное занятие.</AndroidAssimilator.baseDescription>

</LanguageData>
