<?xml version="1.0" encoding="utf-8"?>
<LanguageData>

	<!-- Добавлены недостающие строки русской локализации, сообщите разработчику.

	EN: negligible (no effect) -->
	<VCE_Cholesterol.stages.negligible_no_effect.label>почти в норме</VCE_Cholesterol.stages.negligible_no_effect.label>
	<!-- EN: minor (no effect) -->
	<VCE_Cholesterol.stages.minor_no_effect.label>чуть выше нормы</VCE_Cholesterol.stages.minor_no_effect.label>
	<!-- EN: major -->
	<VCE_Cholesterol.stages.major.label>выше нормы</VCE_Cholesterol.stages.major.label>
	<!-- EN: extreme -->
	<VCE_Cholesterol.stages.extreme.label>высокий уровень</VCE_Cholesterol.stages.extreme.label>

	<!-- EN: negligible (no effect) -->
	<VCE_Diabetes.stages.negligible_no_effect.label>начальный</VCE_Diabetes.stages.negligible_no_effect.label>
	<!-- EN: minor (no effect) -->
	<VCE_Diabetes.stages.minor_no_effect.label>лёгкий</VCE_Diabetes.stages.minor_no_effect.label>
	<!-- EN: major -->
	<VCE_Diabetes.stages.major.label>серьёзный</VCE_Diabetes.stages.major.label>
	<!-- EN: extreme -->
	<VCE_Diabetes.stages.extreme.label>тяжёлый</VCE_Diabetes.stages.extreme.label>

	<!-- EN: negligible (no effect) -->
	<VCE_HighBloodPressure.stages.negligible_no_effect.label>начальное</VCE_HighBloodPressure.stages.negligible_no_effect.label>
	<!-- EN: minor (no effect) -->
	<VCE_HighBloodPressure.stages.minor_no_effect.label>лёгкое</VCE_HighBloodPressure.stages.minor_no_effect.label>
	<!-- EN: major -->
	<VCE_HighBloodPressure.stages.major.label>серьёзное</VCE_HighBloodPressure.stages.major.label>
	<!-- EN: extreme -->
	<VCE_HighBloodPressure.stages.extreme.label>тяжёлое</VCE_HighBloodPressure.stages.extreme.label>

	<!-- Исправлена неточность, сообщите разработчику.

	Оригинал: ...очень калорийен. Снижает уровень голода на 15%... -->
	<VCE_ConsumedMayo.description>Майонез, хотя и ужасен для здоровья, обладает приятным запахом и очень калориен. Уменьшает голод на 15% в течение 24 часов.</VCE_ConsumedMayo.description>
	<!-- Оригинал: потреблён нектар агавы... -->
	<VCE_ConsumedAgave.label>потреблён экстракт агавы (из блюда)</VCE_ConsumedAgave.label>
	<!-- Оригинал: Полусладкий нектар, известный... -->
	<VCE_ConsumedAgave.description>Эссенция из агавы — это концентрированный полусладкий экстракт из её листьев, известный своими целебными и противовоспалительными свойствами. Повышает скорость иммунизации на 15% в течение 24 часов.</VCE_ConsumedAgave.description>
	<!-- Оригинал: ...Увеличивает характеристики манипуляции за 24 часа... -->
	<VCE_ConsumedSpices.description>Потреблено множество ароматических и острых специй. Увеличивает характеристики манипуляции на 10% в течение 24 часов.</VCE_ConsumedSpices.description>
	<!-- Оригиналы: съедено блюдо на гриле -->
	<VCE_WellFed.label>сытная еда (гриль)</VCE_WellFed.label>
	<VCE_WellFedSimple.label>сытная еда (гриль)</VCE_WellFedSimple.label>
	<VCE_WellFedFine.label>сытная еда (гриль)</VCE_WellFedFine.label>
	<VCE_WellFedLavish.label>сытная еда (гриль)</VCE_WellFedLavish.label>
	<VCE_WellFedGourmet.label>сытная еда (гриль)</VCE_WellFedGourmet.label>
	<!-- Описание устарело, заодно добавлена экспрессия.
	Оригиналы: Съедено вкусное блюдо с гриля. Снижает уровень голода на 25% в течение 12 часов. -->
	<VCE_WellFed.description>Съев горячее мясное блюдо с гриля, целый день чувствуешь сытость.</VCE_WellFed.description>
	<VCE_WellFedSimple.description>Съев горячее мясное блюдо с гриля, целый день чувствуешь сытость.</VCE_WellFedSimple.description>
	<VCE_WellFedFine.description>Съев горячее мясное блюдо с гриля, целый день чувствуешь сытость.</VCE_WellFedFine.description>
	<VCE_WellFedLavish.description>Съев горячее мясное блюдо с гриля, целый день чувствуешь сытость.</VCE_WellFedLavish.description>
	<VCE_WellFedGourmet.description>Съев горячее мясное блюдо с гриля, целый день чувствуешь сытость.</VCE_WellFedGourmet.description>
	<!-- Оригинал: Воскрешающие механиты воскресят эту пешку, пока они активны в её теле. Эффект длится 12 часов. -->
	<VCE_ConsumedDigestibleResurrectorNanites.description>В случае чего, механиты воскресят этого поселенца. Они будут находиться в пищеварительном тракте около 12 часов.</VCE_ConsumedDigestibleResurrectorNanites.description>
	<!-- Оригинал: ...подвижность на 15% за 24 часа. -->
	<VCE_SugarRush.description>Сахар легко превращается организмом в энергию. Увеличивает подвижность на 15% в течение суток.</VCE_SugarRush.description>
	<!-- Игра рассчитана на одно поселение.
	Оригинал: Этот колонист потребил... -->
	<VCE_AteGourmetMeal.description>Этот поселенец потребил невероятно вкусную еду.</VCE_AteGourmetMeal.description>

	<!-- Оригинал: Диабет - это...Симптомы часто включают...мочеиспускание, повышенную жажду и повышенный аппетит. -->
	<VCE_Diabetes.description>Диабет — это группа метаболических нарушений, характеризующихся высоким уровнем сахара в крови в течение длительного периода времени. Симптомы включают частое мочеиспускание, усиление голода и жажды.</VCE_Diabetes.description>
	<!-- Оригинал: ...является распространенным состоянием...сила крови на стенках артерий...высока, что может в конечном итоге вызвать...здоровьем, такие как болезни... -->
	<VCE_HighBloodPressure.description>Высокое кровяное давление, также называемое гипертонией, является распространённым состоянием, при котором долговременная сила давления крови на стенки артерий достаточно высока, чтобы постепенно вызвать проблемы со здоровьем, например, болезни сердца.</VCE_HighBloodPressure.description>

	<!-- Исправление согласно концепции «12+».

	Оригинал: Ферментированная паста из...бобов. Соевый...придания пище насыщенного вкуса "умами". Соевый соус содержит в 10 раз больше антиоксидантов красного вина, и может помочь предотвратить... -->
	<VCE_ConsumedSoySauce.description>Паста из соевых бобов после ферментации превращается в тёмную жидкость с характерным запахом. Соевый соус можно использовать в качестве пищевой добавки для придания насыщенного вкуса «умами». Такие блюда будут содержать много антиоксидантов и помогут предотвратить сердечно-сосудистые заболевания.</VCE_ConsumedSoySauce.description>

</LanguageData>
